{"nodes": [{"id": "c_ai_knowledge_workspace_handy_main_src_components_editor_selectionbubbleplugin_tsx", "label": "selectionBubblePlugin.tsx", "file_type": "code", "source_file": "C:\\AI_knowledge_workspace\\Handy-main\\src\\components\\editor\\selectionBubblePlugin.tsx", "source_location": "L1"}, {"id": "selectionbubbleplugin_selectioninsideeditor", "label": "selectionInsideEditor()", "file_type": "code", "source_file": "C:\\AI_knowledge_workspace\\Handy-main\\src\\components\\editor\\selectionBubblePlugin.tsx", "source_location": "L46"}, {"id": "selectionbubbleplugin_bubbleposition", "label": "bubblePosition()", "file_type": "code", "source_file": "C:\\AI_knowledge_workspace\\Handy-main\\src\\components\\editor\\selectionBubblePlugin.tsx", "source_location": "L66"}, {"id": "selectionbubbleplugin_bubblez", "label": "bubbleZ()", "file_type": "code", "source_file": "C:\\AI_knowledge_workspace\\Handy-main\\src\\components\\editor\\selectionBubblePlugin.tsx", "source_location": "L90"}, {"id": "selectionbubbleplugin_runlinkshortcut", "label": "runLinkShortcut()", "file_type": "code", "source_file": "C:\\AI_knowledge_workspace\\Handy-main\\src\\components\\editor\\selectionBubblePlugin.tsx", "source_location": "L94"}, {"id": "selectionbubbleplugin_onsel", "label": "onSel()", "file_type": "code", "source_file": "C:\\AI_knowledge_workspace\\Handy-main\\src\\components\\editor\\selectionBubblePlugin.tsx", "source_location": "L180"}, {"id": "selectionbubbleplugin_close", "label": "close()", "file_type": "code", "source_file": "C:\\AI_knowledge_workspace\\Handy-main\\src\\components\\editor\\selectionBubblePlugin.tsx", "source_location": "L196"}, {"id": "selectionbubbleplugin_toolbtn", "label": "toolBtn()", "file_type": "code", "source_file": "C:\\AI_knowledge_workspace\\Handy-main\\src\\components\\editor\\selectionBubblePlugin.tsx", "source_location": "L300"}, {"id": "selectionbubbleplugin_init", "label": "init()", "file_type": "code", "source_file": "C:\\AI_knowledge_workspace\\Handy-main\\src\\components\\editor\\selectionBubblePlugin.tsx", "source_location": "L516"}], "edges": [{"source": "c_ai_knowledge_workspace_handy_main_src_components_editor_selectionbubbleplugin_tsx", "target": "editor", "relation": "imports_from", "confidence": "EXTRACTED", "source_file": "C:\\AI_knowledge_workspace\\Handy-main\\src\\components\\editor\\selectionBubblePlugin.tsx", "source_location": "L5", "weight": 1.0}, {"source": "c_ai_knowledge_workspace_handy_main_src_components_editor_selectionbubbleplugin_tsx", "target": "lexicalcomposercontext", "relation": "imports_from", "confidence": "EXTRACTED", "source_file": "C:\\AI_knowledge_workspace\\Handy-main\\src\\components\\editor\\selectionBubblePlugin.tsx", "source_location": "L14", "weight": 1.0}, {"source": "c_ai_knowledge_workspace_handy_main_src_components_editor_selectionbubbleplugin_tsx", "target": "gurx", "relation": "imports_from", "confidence": "EXTRACTED", "source_file": "C:\\AI_knowledge_workspace\\Handy-main\\src\\components\\editor\\selectionBubblePlugin.tsx", "source_location": "L15", "weight": 1.0}, {"source": "c_ai_knowledge_workspace_handy_main_src_components_editor_selectionbubbleplugin_tsx", "target": "lucide_react", "relation": "imports_from", "confidence": "EXTRACTED", "source_file": "C:\\AI_knowledge_workspace\\Handy-main\\src\\components\\editor\\selectionBubblePlugin.tsx", "source_location": "L16", "weight": 1.0}, {"source": "c_ai_knowledge_workspace_handy_main_src_components_editor_selectionbubbleplugin_tsx", "target": "editor", "relation": "imports_from", "confidence": "EXTRACTED", "source_file": "C:\\AI_knowledge_workspace\\Handy-main\\src\\components\\editor\\selectionBubblePlugin.tsx", "source_location": "L32", "weight": 1.0}, {"source": "c_ai_knowledge_workspace_handy_main_src_components_editor_selectionbubbleplugin_tsx", "target": "lexical", "relation": "imports_from", "confidence": "EXTRACTED", "source_file": "C:\\AI_knowledge_workspace\\Handy-main\\src\\components\\editor\\selectionBubblePlugin.tsx", "source_location": "L38", "weight": 1.0}, {"source": "c_ai_knowledge_workspace_handy_main_src_components_editor_selectionbubbleplugin_tsx", "target": "react", "relation": "imports_from", "confidence": "EXTRACTED", "source_file": "C:\\AI_knowledge_workspace\\Handy-main\\src\\components\\editor\\selectionBubblePlugin.tsx", "source_location": "L39", "weight": 1.0}, {"source": "c_ai_knowledge_workspace_handy_main_src_components_editor_selectionbubbleplugin_tsx", "target": "react_dom", "relation": "imports_from", "confidence": "EXTRACTED", "source_file": "C:\\AI_knowledge_workspace\\Handy-main\\src\\components\\editor\\selectionBubblePlugin.tsx", "source_location": "L40", "weight": 1.0}, {"source": "c_ai_knowledge_workspace_handy_main_src_components_editor_selectionbubbleplugin_tsx", "target": "react_i18next", "relation": "imports_from", "confidence": "EXTRACTED", "source_file": "C:\\AI_knowledge_workspace\\Handy-main\\src\\components\\editor\\selectionBubblePlugin.tsx", "source_location": "L41", "weight": 1.0}, {"source": "c_ai_knowledge_workspace_handy_main_src_components_editor_selectionbubbleplugin_tsx", "target": "workspacefloatinglayer", "relation": "imports_from", "confidence": "EXTRACTED", "source_file": "C:\\AI_knowledge_workspace\\Handy-main\\src\\components\\editor\\selectionBubblePlugin.tsx", "source_location": "L42", "weight": 1.0}, {"source": "c_ai_knowledge_workspace_handy_main_src_components_editor_selectionbubbleplugin_tsx", "target": "selectionbubbleplugin_selectioninsideeditor", "relation": "contains", "confidence": "EXTRACTED", "source_file": "C:\\AI_knowledge_workspace\\Handy-main\\src\\components\\editor\\selectionBubblePlugin.tsx", "source_location": "L46", "weight": 1.0}, {"source": "c_ai_knowledge_workspace_handy_main_src_components_editor_selectionbubbleplugin_tsx", "target": "selectionbubbleplugin_bubbleposition", "relation": "contains", "confidence": "EXTRACTED", "source_file": "C:\\AI_knowledge_workspace\\Handy-main\\src\\components\\editor\\selectionBubblePlugin.tsx", "source_location": "L66", "weight": 1.0}, {"source": "c_ai_knowledge_workspace_handy_main_src_components_editor_selectionbubbleplugin_tsx", "target": "selectionbubbleplugin_bubblez", "relation": "contains", "confidence": "EXTRACTED", "source_file": "C:\\AI_knowledge_workspace\\Handy-main\\src\\components\\editor\\selectionBubblePlugin.tsx", "source_location": "L90", "weight": 1.0}, {"source": "c_ai_knowledge_workspace_handy_main_src_components_editor_selectionbubbleplugin_tsx", "target": "selectionbubbleplugin_runlinkshortcut", "relation": "contains", "confidence": "EXTRACTED", "source_file": "C:\\AI_knowledge_workspace\\Handy-main\\src\\components\\editor\\selectionBubblePlugin.tsx", "source_location": "L94", "weight": 1.0}, {"source": "c_ai_knowledge_workspace_handy_main_src_components_editor_selectionbubbleplugin_tsx", "target": "selectionbubbleplugin_onsel", "relation": "contains", "confidence": "EXTRACTED", "source_file": "C:\\AI_knowledge_workspace\\Handy-main\\src\\components\\editor\\selectionBubblePlugin.tsx", "source_location": "L180", "weight": 1.0}, {"source": "c_ai_knowledge_workspace_handy_main_src_components_editor_selectionbubbleplugin_tsx", "target": "selectionbubbleplugin_close", "relation": "contains", "confidence": "EXTRACTED", "source_file": "C:\\AI_knowledge_workspace\\Handy-main\\src\\components\\editor\\selectionBubblePlugin.tsx", "source_location": "L196", "weight": 1.0}, {"source": "c_ai_knowledge_workspace_handy_main_src_components_editor_selectionbubbleplugin_tsx", "target": "selectionbubbleplugin_toolbtn", "relation": "contains", "confidence": "EXTRACTED", "source_file": "C:\\AI_knowledge_workspace\\Handy-main\\src\\components\\editor\\selectionBubblePlugin.tsx", "source_location": "L300", "weight": 1.0}, {"source": "c_ai_knowledge_workspace_handy_main_src_components_editor_selectionbubbleplugin_tsx", "target": "selectionbubbleplugin_init", "relation": "contains", "confidence": "EXTRACTED", "source_file": "C:\\AI_knowledge_workspace\\Handy-main\\src\\components\\editor\\selectionBubblePlugin.tsx", "source_location": "L516", "weight": 1.0}], "raw_calls": [{"caller_nid": "selectionbubbleplugin_selectioninsideeditor", "callee": "getSelection", "source_file": "C:\\AI_knowledge_workspace\\Handy-main\\src\\components\\editor\\selectionBubblePlugin.tsx", "source_location": "L47"}, {"caller_nid": "selectionbubbleplugin_selectioninsideeditor", "callee": "getRootElement", "source_file": "C:\\AI_knowledge_workspace\\Handy-main\\src\\components\\editor\\selectionBubblePlugin.tsx", "source_location": "L50"}, {"caller_nid": "selectionbubbleplugin_selectioninsideeditor", "callee": "contains", "source_file": "C:\\AI_knowledge_workspace\\Handy-main\\src\\components\\editor\\selectionBubblePlugin.tsx", "source_location": "L55"}, {"caller_nid": "selectionbubbleplugin_bubbleposition", "callee": "getSelection", "source_file": "C:\\AI_knowledge_workspace\\Handy-main\\src\\components\\editor\\selectionBubblePlugin.tsx", "source_location": "L67"}, {"caller_nid": "selectionbubbleplugin_bubbleposition", "callee": "getBoundingClientRect", "source_file": "C:\\AI_knowledge_workspace\\Handy-main\\src\\components\\editor\\selectionBubblePlugin.tsx", "source_location": "L70"}, {"caller_nid": "selectionbubbleplugin_bubbleposition", "callee": "getRangeAt", "source_file": "C:\\AI_knowledge_workspace\\Handy-main\\src\\components\\editor\\selectionBubblePlugin.tsx", "source_location": "L70"}, {"caller_nid": "selectionbubbleplugin_bubbleposition", "callee": "max", "source_file": "C:\\AI_knowledge_workspace\\Handy-main\\src\\components\\editor\\selectionBubblePlugin.tsx", "source_location": "L81"}, {"caller_nid": "selectionbubbleplugin_bubbleposition", "callee": "min", "source_file": "C:\\AI_knowledge_workspace\\Handy-main\\src\\components\\editor\\selectionBubblePlugin.tsx", "source_location": "L83"}, {"caller_nid": "selectionbubbleplugin_bubbleposition", "callee": "max", "source_file": "C:\\AI_knowledge_workspace\\Handy-main\\src\\components\\editor\\selectionBubblePlugin.tsx", "source_location": "L85"}, {"caller_nid": "selectionbubbleplugin_bubblez", "callee": "parseInt", "source_file": "C:\\AI_knowledge_workspace\\Handy-main\\src\\components\\editor\\selectionBubblePlugin.tsx", "source_location": "L91"}, {"caller_nid": "selectionbubbleplugin_bubblez", "callee": "workspaceFloatingZ", "source_file": "C:\\AI_knowledge_workspace\\Handy-main\\src\\components\\editor\\selectionBubblePlugin.tsx", "source_location": "L91"}, {"caller_nid": "selectionbubbleplugin_runlinkshortcut", "callee": "getRootElement", "source_file": "C:\\AI_knowledge_workspace\\Handy-main\\src\\components\\editor\\selectionBubblePlugin.tsx", "source_location": "L95"}, {"caller_nid": "selectionbubbleplugin_runlinkshortcut", "callee": "querySelector", "source_file": "C:\\AI_knowledge_workspace\\Handy-main\\src\\components\\editor\\selectionBubblePlugin.tsx", "source_location": "L96"}, {"caller_nid": "selectionbubbleplugin_runlinkshortcut", "callee": "test", "source_file": "C:\\AI_knowledge_workspace\\Handy-main\\src\\components\\editor\\selectionBubblePlugin.tsx", "source_location": "L99"}, {"caller_nid": "selectionbubbleplugin_runlinkshortcut", "callee": "focus", "source_file": "C:\\AI_knowledge_workspace\\Handy-main\\src\\components\\editor\\selectionBubblePlugin.tsx", "source_location": "L100"}, {"caller_nid": "selectionbubbleplugin_runlinkshortcut", "callee": "dispatchEvent", "source_file": "C:\\AI_knowledge_workspace\\Handy-main\\src\\components\\editor\\selectionBubblePlugin.tsx", "source_location": "L101"}, {"caller_nid": "selectionbubbleplugin_onsel", "callee": "cancelAnimationFrame", "source_file": "C:\\AI_knowledge_workspace\\Handy-main\\src\\components\\editor\\selectionBubblePlugin.tsx", "source_location": "L181"}, {"caller_nid": "selectionbubbleplugin_onsel", "callee": "requestAnimationFrame", "source_file": "C:\\AI_knowledge_workspace\\Handy-main\\src\\components\\editor\\selectionBubblePlugin.tsx", "source_location": "L182"}, {"caller_nid": "selectionbubbleplugin_close", "callee": "contains", "source_file": "C:\\AI_knowledge_workspace\\Handy-main\\src\\components\\editor\\selectionBubblePlugin.tsx", "source_location": "L199"}, {"caller_nid": "selectionbubbleplugin_close", "callee": "setMoreOpen", "source_file": "C:\\AI_knowledge_workspace\\Handy-main\\src\\components\\editor\\selectionBubblePlugin.tsx", "source_location": "L200"}, {"caller_nid": "selectionbubbleplugin_init", "callee": "pubIn", "source_file": "C:\\AI_knowledge_workspace\\Handy-main\\src\\components\\editor\\selectionBubblePlugin.tsx", "source_location": "L517"}]}