{"nodes": [{"id": "c_ai_knowledge_workspace_handy_main_src_tauri_src_actions_rs", "label": "actions.rs", "file_type": "code", "source_file": "C:\\AI_knowledge_workspace\\Handy-main\\src-tauri\\src\\actions.rs", "source_location": "L1"}, {"id": "actions_recordingerrorevent", "label": "RecordingErrorEvent", "file_type": "code", "source_file": "C:\\AI_knowledge_workspace\\Handy-main\\src-tauri\\src\\actions.rs", "source_location": "L31"}, {"id": "actions_finishguard", "label": "FinishGuard", "file_type": "code", "source_file": "C:\\AI_knowledge_workspace\\Handy-main\\src-tauri\\src\\actions.rs", "source_location": "L38"}, {"id": "actions_finishguard_drop", "label": ".drop()", "file_type": "code", "source_file": "C:\\AI_knowledge_workspace\\Handy-main\\src-tauri\\src\\actions.rs", "source_location": "L40"}, {"id": "actions_finalize_transcription_ui", "label": "finalize_transcription_ui()", "file_type": "code", "source_file": "C:\\AI_knowledge_workspace\\Handy-main\\src-tauri\\src\\actions.rs", "source_location": "L47"}, {"id": "actions_shortcutaction", "label": "ShortcutAction", "file_type": "code", "source_file": "C:\\AI_knowledge_workspace\\Handy-main\\src-tauri\\src\\actions.rs", "source_location": "L78"}, {"id": "actions_transcribeaction", "label": "TranscribeAction", "file_type": "code", "source_file": "C:\\AI_knowledge_workspace\\Handy-main\\src-tauri\\src\\actions.rs", "source_location": "L84"}, {"id": "actions_strip_invisible_chars", "label": "strip_invisible_chars()", "file_type": "code", "source_file": "C:\\AI_knowledge_workspace\\Handy-main\\src-tauri\\src\\actions.rs", "source_location": "L92"}, {"id": "actions_build_system_prompt", "label": "build_system_prompt()", "file_type": "code", "source_file": "C:\\AI_knowledge_workspace\\Handy-main\\src-tauri\\src\\actions.rs", "source_location": "L98"}, {"id": "actions_post_process_transcription", "label": "post_process_transcription()", "file_type": "code", "source_file": "C:\\AI_knowledge_workspace\\Handy-main\\src-tauri\\src\\actions.rs", "source_location": "L102"}, {"id": "actions_maybe_convert_chinese_variant", "label": "maybe_convert_chinese_variant()", "file_type": "code", "source_file": "C:\\AI_knowledge_workspace\\Handy-main\\src-tauri\\src\\actions.rs", "source_location": "L317"}, {"id": "actions_processedtranscription", "label": "ProcessedTranscription", "file_type": "code", "source_file": "C:\\AI_knowledge_workspace\\Handy-main\\src-tauri\\src\\actions.rs", "source_location": "L361"}, {"id": "actions_voice_memo_daily_title_for_local_date", "label": "voice_memo_daily_title_for_local_date()", "file_type": "code", "source_file": "C:\\AI_knowledge_workspace\\Handy-main\\src-tauri\\src\\actions.rs", "source_location": "L368"}, {"id": "actions_legacy_voice_memo_daily_title_for_local_date", "label": "legacy_voice_memo_daily_title_for_local_date()", "file_type": "code", "source_file": "C:\\AI_knowledge_workspace\\Handy-main\\src-tauri\\src\\actions.rs", "source_location": "L375"}, {"id": "actions_migrate_legacy_voice_memo_title", "label": "migrate_legacy_voice_memo_title()", "file_type": "code", "source_file": "C:\\AI_knowledge_workspace\\Handy-main\\src-tauri\\src\\actions.rs", "source_location": "L386"}, {"id": "actions_create_markdown_note_content", "label": "create_markdown_note_content()", "file_type": "code", "source_file": "C:\\AI_knowledge_workspace\\Handy-main\\src-tauri\\src\\actions.rs", "source_location": "L435"}, {"id": "actions_append_markdown_note_content", "label": "append_markdown_note_content()", "file_type": "code", "source_file": "C:\\AI_knowledge_workspace\\Handy-main\\src-tauri\\src\\actions.rs", "source_location": "L439"}, {"id": "actions_directive_escape_path", "label": "directive_escape_path()", "file_type": "code", "source_file": "C:\\AI_knowledge_workspace\\Handy-main\\src-tauri\\src\\actions.rs", "source_location": "L451"}, {"id": "actions_voice_memo_recording_block", "label": "voice_memo_recording_block()", "file_type": "code", "source_file": "C:\\AI_knowledge_workspace\\Handy-main\\src-tauri\\src\\actions.rs", "source_location": "L456"}, {"id": "actions_append_transcription_to_voice_doc", "label": "append_transcription_to_voice_doc()", "file_type": "code", "source_file": "C:\\AI_knowledge_workspace\\Handy-main\\src-tauri\\src\\actions.rs", "source_location": "L469"}, {"id": "actions_maybe_create_note_from_transcription", "label": "maybe_create_note_from_transcription()", "file_type": "code", "source_file": "C:\\AI_knowledge_workspace\\Handy-main\\src-tauri\\src\\actions.rs", "source_location": "L528"}, {"id": "actions_process_transcription_output", "label": "process_transcription_output()", "file_type": "code", "source_file": "C:\\AI_knowledge_workspace\\Handy-main\\src-tauri\\src\\actions.rs", "source_location": "L724"}, {"id": "actions_transcribeaction_start", "label": ".start()", "file_type": "code", "source_file": "C:\\AI_knowledge_workspace\\Handy-main\\src-tauri\\src\\actions.rs", "source_location": "L765"}, {"id": "actions_transcribeaction_stop", "label": ".stop()", "file_type": "code", "source_file": "C:\\AI_knowledge_workspace\\Handy-main\\src-tauri\\src\\actions.rs", "source_location": "L867"}, {"id": "actions_cancelaction", "label": "CancelAction", "file_type": "code", "source_file": "C:\\AI_knowledge_workspace\\Handy-main\\src-tauri\\src\\actions.rs", "source_location": "L1059"}, {"id": "actions_cancelaction_start", "label": ".start()", "file_type": "code", "source_file": "C:\\AI_knowledge_workspace\\Handy-main\\src-tauri\\src\\actions.rs", "source_location": "L1062"}, {"id": "actions_cancelaction_stop", "label": ".stop()", "file_type": "code", "source_file": "C:\\AI_knowledge_workspace\\Handy-main\\src-tauri\\src\\actions.rs", "source_location": "L1066"}, {"id": "actions_testaction", "label": "TestAction", "file_type": "code", "source_file": "C:\\AI_knowledge_workspace\\Handy-main\\src-tauri\\src\\actions.rs", "source_location": "L1072"}, {"id": "actions_testaction_start", "label": ".start()", "file_type": "code", "source_file": "C:\\AI_knowledge_workspace\\Handy-main\\src-tauri\\src\\actions.rs", "source_location": "L1075"}, {"id": "actions_testaction_stop", "label": ".stop()", "file_type": "code", "source_file": "C:\\AI_knowledge_workspace\\Handy-main\\src-tauri\\src\\actions.rs", "source_location": "L1084"}, {"id": "actions_create_markdown_note_content_returns_trimmed_text", "label": "create_markdown_note_content_returns_trimmed_text()", "file_type": "code", "source_file": "C:\\AI_knowledge_workspace\\Handy-main\\src-tauri\\src\\actions.rs", "source_location": "L1123"}, {"id": "actions_append_markdown_note_content_joins_with_blank_line", "label": "append_markdown_note_content_joins_with_blank_line()", "file_type": "code", "source_file": "C:\\AI_knowledge_workspace\\Handy-main\\src-tauri\\src\\actions.rs", "source_location": "L1129"}], "edges": [{"source": "c_ai_knowledge_workspace_handy_main_src_tauri_src_actions_rs", "target": "apple_intelligence", "relation": "imports_from", "confidence": "EXTRACTED", "source_file": "C:\\AI_knowledge_workspace\\Handy-main\\src-tauri\\src\\actions.rs", "source_location": "L2", "weight": 1.0}, {"source": "c_ai_knowledge_workspace_handy_main_src_tauri_src_actions_rs", "target": "audio_feedback", "relation": "imports_from", "confidence": "EXTRACTED", "source_file": "C:\\AI_knowledge_workspace\\Handy-main\\src-tauri\\src\\actions.rs", "source_location": "L3", "weight": 1.0}, {"source": "c_ai_knowledge_workspace_handy_main_src_tauri_src_actions_rs", "target": "audio_toolkit", "relation": "imports_from", "confidence": "EXTRACTED", "source_file": "C:\\AI_knowledge_workspace\\Handy-main\\src-tauri\\src\\actions.rs", "source_location": "L4", "weight": 1.0}, {"source": "c_ai_knowledge_workspace_handy_main_src_tauri_src_actions_rs", "target": "audiorecordingmanager", "relation": "imports_from", "confidence": "EXTRACTED", "source_file": "C:\\AI_knowledge_workspace\\Handy-main\\src-tauri\\src\\actions.rs", "source_location": "L5", "weight": 1.0}, {"source": "c_ai_knowledge_workspace_handy_main_src_tauri_src_actions_rs", "target": "historymanager", "relation": "imports_from", "confidence": "EXTRACTED", "source_file": "C:\\AI_knowledge_workspace\\Handy-main\\src-tauri\\src\\actions.rs", "source_location": "L6", "weight": 1.0}, {"source": "c_ai_knowledge_workspace_handy_main_src_tauri_src_actions_rs", "target": "appstate", "relation": "imports_from", "confidence": "EXTRACTED", "source_file": "C:\\AI_knowledge_workspace\\Handy-main\\src-tauri\\src\\actions.rs", "source_location": "L7", "weight": 1.0}, {"source": "c_ai_knowledge_workspace_handy_main_src_tauri_src_actions_rs", "target": "transcriptionmanager", "relation": "imports_from", "confidence": "EXTRACTED", "source_file": "C:\\AI_knowledge_workspace\\Handy-main\\src-tauri\\src\\actions.rs", "source_location": "L8", "weight": 1.0}, {"source": "c_ai_knowledge_workspace_handy_main_src_tauri_src_actions_rs", "target": "voicesessionmanager", "relation": "imports_from", "confidence": "EXTRACTED", "source_file": "C:\\AI_knowledge_workspace\\Handy-main\\src-tauri\\src\\actions.rs", "source_location": "L9", "weight": 1.0}, {"source": "c_ai_knowledge_workspace_handy_main_src_tauri_src_actions_rs", "target": "settings", "relation": "imports_from", "confidence": "EXTRACTED", "source_file": "C:\\AI_knowledge_workspace\\Handy-main\\src-tauri\\src\\actions.rs", "source_location": "L10", "weight": 1.0}, {"source": "c_ai_knowledge_workspace_handy_main_src_tauri_src_actions_rs", "target": "shortcut", "relation": "imports_from", "confidence": "EXTRACTED", "source_file": "C:\\AI_knowledge_workspace\\Handy-main\\src-tauri\\src\\actions.rs", "source_location": "L13", "weight": 1.0}, {"source": "c_ai_knowledge_workspace_handy_main_src_tauri_src_actions_rs", "target": "tray", "relation": "imports_from", "confidence": "EXTRACTED", "source_file": "C:\\AI_knowledge_workspace\\Handy-main\\src-tauri\\src\\actions.rs", "source_location": "L14", "weight": 1.0}, {"source": "c_ai_knowledge_workspace_handy_main_src_tauri_src_actions_rs", "target": "utils", "relation": "imports_from", "confidence": "EXTRACTED", "source_file": "C:\\AI_knowledge_workspace\\Handy-main\\src-tauri\\src\\actions.rs", "source_location": "L15", "weight": 1.0}, {"source": "c_ai_knowledge_workspace_handy_main_src_tauri_src_actions_rs", "target": "transcription_workspace", "relation": "imports_from", "confidence": "EXTRACTED", "source_file": "C:\\AI_knowledge_workspace\\Handy-main\\src-tauri\\src\\actions.rs", "source_location": "L18", "weight": 1.0}, {"source": "c_ai_knowledge_workspace_handy_main_src_tauri_src_actions_rs", "target": "transcriptioncoordinator", "relation": "imports_from", "confidence": "EXTRACTED", "source_file": "C:\\AI_knowledge_workspace\\Handy-main\\src-tauri\\src\\actions.rs", "source_location": "L19", "weight": 1.0}, {"source": "c_ai_knowledge_workspace_handy_main_src_tauri_src_actions_rs", "target": "datelike", "relation": "imports_from", "confidence": "EXTRACTED", "source_file": "C:\\AI_knowledge_workspace\\Handy-main\\src-tauri\\src\\actions.rs", "source_location": "L20", "weight": 1.0}, {"source": "c_ai_knowledge_workspace_handy_main_src_tauri_src_actions_rs", "target": "ferrous_opencc", "relation": "imports_from", "confidence": "EXTRACTED", "source_file": "C:\\AI_knowledge_workspace\\Handy-main\\src-tauri\\src\\actions.rs", "source_location": "L21", "weight": 1.0}, {"source": "c_ai_knowledge_workspace_handy_main_src_tauri_src_actions_rs", "target": "log", "relation": "imports_from", "confidence": "EXTRACTED", "source_file": "C:\\AI_knowledge_workspace\\Handy-main\\src-tauri\\src\\actions.rs", "source_location": "L22", "weight": 1.0}, {"source": "c_ai_knowledge_workspace_handy_main_src_tauri_src_actions_rs", "target": "lazy", "relation": "imports_from", "confidence": "EXTRACTED", "source_file": "C:\\AI_knowledge_workspace\\Handy-main\\src-tauri\\src\\actions.rs", "source_location": "L23", "weight": 1.0}, {"source": "c_ai_knowledge_workspace_handy_main_src_tauri_src_actions_rs", "target": "hashmap", "relation": "imports_from", "confidence": "EXTRACTED", "source_file": "C:\\AI_knowledge_workspace\\Handy-main\\src-tauri\\src\\actions.rs", "source_location": "L24", "weight": 1.0}, {"source": "c_ai_knowledge_workspace_handy_main_src_tauri_src_actions_rs", "target": "arc", "relation": "imports_from", "confidence": "EXTRACTED", "source_file": "C:\\AI_knowledge_workspace\\Handy-main\\src-tauri\\src\\actions.rs", "source_location": "L25", "weight": 1.0}, {"source": "c_ai_knowledge_workspace_handy_main_src_tauri_src_actions_rs", "target": "instant", "relation": "imports_from", "confidence": "EXTRACTED", "source_file": "C:\\AI_knowledge_workspace\\Handy-main\\src-tauri\\src\\actions.rs", "source_location": "L26", "weight": 1.0}, {"source": "c_ai_knowledge_workspace_handy_main_src_tauri_src_actions_rs", "target": "manager", "relation": "imports_from", "confidence": "EXTRACTED", "source_file": "C:\\AI_knowledge_workspace\\Handy-main\\src-tauri\\src\\actions.rs", "source_location": "L27", "weight": 1.0}, {"source": "c_ai_knowledge_workspace_handy_main_src_tauri_src_actions_rs", "target": "tauri", "relation": "imports_from", "confidence": "EXTRACTED", "source_file": "C:\\AI_knowledge_workspace\\Handy-main\\src-tauri\\src\\actions.rs", "source_location": "L28", "weight": 1.0}, {"source": "c_ai_knowledge_workspace_handy_main_src_tauri_src_actions_rs", "target": "actions_recordingerrorevent", "relation": "contains", "confidence": "EXTRACTED", "source_file": "C:\\AI_knowledge_workspace\\Handy-main\\src-tauri\\src\\actions.rs", "source_location": "L31", "weight": 1.0}, {"source": "c_ai_knowledge_workspace_handy_main_src_tauri_src_actions_rs", "target": "actions_finishguard", "relation": "contains", "confidence": "EXTRACTED", "source_file": "C:\\AI_knowledge_workspace\\Handy-main\\src-tauri\\src\\actions.rs", "source_location": "L38", "weight": 1.0}, {"source": "actions_finishguard", "target": "actions_finishguard_drop", "relation": "method", "confidence": "EXTRACTED", "source_file": "C:\\AI_knowledge_workspace\\Handy-main\\src-tauri\\src\\actions.rs", "source_location": "L40", "weight": 1.0}, {"source": "c_ai_knowledge_workspace_handy_main_src_tauri_src_actions_rs", "target": "actions_finalize_transcription_ui", "relation": "contains", "confidence": "EXTRACTED", "source_file": "C:\\AI_knowledge_workspace\\Handy-main\\src-tauri\\src\\actions.rs", "source_location": "L47", "weight": 1.0}, {"source": "c_ai_knowledge_workspace_handy_main_src_tauri_src_actions_rs", "target": "actions_shortcutaction", "relation": "contains", "confidence": "EXTRACTED", "source_file": "C:\\AI_knowledge_workspace\\Handy-main\\src-tauri\\src\\actions.rs", "source_location": "L78", "weight": 1.0}, {"source": "c_ai_knowledge_workspace_handy_main_src_tauri_src_actions_rs", "target": "actions_transcribeaction", "relation": "contains", "confidence": "EXTRACTED", "source_file": "C:\\AI_knowledge_workspace\\Handy-main\\src-tauri\\src\\actions.rs", "source_location": "L84", "weight": 1.0}, {"source": "c_ai_knowledge_workspace_handy_main_src_tauri_src_actions_rs", "target": "actions_strip_invisible_chars", "relation": "contains", "confidence": "EXTRACTED", "source_file": "C:\\AI_knowledge_workspace\\Handy-main\\src-tauri\\src\\actions.rs", "source_location": "L92", "weight": 1.0}, {"source": "c_ai_knowledge_workspace_handy_main_src_tauri_src_actions_rs", "target": "actions_build_system_prompt", "relation": "contains", "confidence": "EXTRACTED", "source_file": "C:\\AI_knowledge_workspace\\Handy-main\\src-tauri\\src\\actions.rs", "source_location": "L98", "weight": 1.0}, {"source": "c_ai_knowledge_workspace_handy_main_src_tauri_src_actions_rs", "target": "actions_post_process_transcription", "relation": "contains", "confidence": "EXTRACTED", "source_file": "C:\\AI_knowledge_workspace\\Handy-main\\src-tauri\\src\\actions.rs", "source_location": "L102", "weight": 1.0}, {"source": "c_ai_knowledge_workspace_handy_main_src_tauri_src_actions_rs", "target": "actions_maybe_convert_chinese_variant", "relation": "contains", "confidence": "EXTRACTED", "source_file": "C:\\AI_knowledge_workspace\\Handy-main\\src-tauri\\src\\actions.rs", "source_location": "L317", "weight": 1.0}, {"source": "c_ai_knowledge_workspace_handy_main_src_tauri_src_actions_rs", "target": "actions_processedtranscription", "relation": "contains", "confidence": "EXTRACTED", "source_file": "C:\\AI_knowledge_workspace\\Handy-main\\src-tauri\\src\\actions.rs", "source_location": "L361", "weight": 1.0}, {"source": "c_ai_knowledge_workspace_handy_main_src_tauri_src_actions_rs", "target": "actions_voice_memo_daily_title_for_local_date", "relation": "contains", "confidence": "EXTRACTED", "source_file": "C:\\AI_knowledge_workspace\\Handy-main\\src-tauri\\src\\actions.rs", "source_location": "L368", "weight": 1.0}, {"source": "c_ai_knowledge_workspace_handy_main_src_tauri_src_actions_rs", "target": "actions_legacy_voice_memo_daily_title_for_local_date", "relation": "contains", "confidence": "EXTRACTED", "source_file": "C:\\AI_knowledge_workspace\\Handy-main\\src-tauri\\src\\actions.rs", "source_location": "L375", "weight": 1.0}, {"source": "c_ai_knowledge_workspace_handy_main_src_tauri_src_actions_rs", "target": "actions_migrate_legacy_voice_memo_title", "relation": "contains", "confidence": "EXTRACTED", "source_file": "C:\\AI_knowledge_workspace\\Handy-main\\src-tauri\\src\\actions.rs", "source_location": "L386", "weight": 1.0}, {"source": "c_ai_knowledge_workspace_handy_main_src_tauri_src_actions_rs", "target": "actions_create_markdown_note_content", "relation": "contains", "confidence": "EXTRACTED", "source_file": "C:\\AI_knowledge_workspace\\Handy-main\\src-tauri\\src\\actions.rs", "source_location": "L435", "weight": 1.0}, {"source": "c_ai_knowledge_workspace_handy_main_src_tauri_src_actions_rs", "target": "actions_append_markdown_note_content", "relation": "contains", "confidence": "EXTRACTED", "source_file": "C:\\AI_knowledge_workspace\\Handy-main\\src-tauri\\src\\actions.rs", "source_location": "L439", "weight": 1.0}, {"source": "c_ai_knowledge_workspace_handy_main_src_tauri_src_actions_rs", "target": "actions_directive_escape_path", "relation": "contains", "confidence": "EXTRACTED", "source_file": "C:\\AI_knowledge_workspace\\Handy-main\\src-tauri\\src\\actions.rs", "source_location": "L451", "weight": 1.0}, {"source": "c_ai_knowledge_workspace_handy_main_src_tauri_src_actions_rs", "target": "actions_voice_memo_recording_block", "relation": "contains", "confidence": "EXTRACTED", "source_file": "C:\\AI_knowledge_workspace\\Handy-main\\src-tauri\\src\\actions.rs", "source_location": "L456", "weight": 1.0}, {"source": "c_ai_knowledge_workspace_handy_main_src_tauri_src_actions_rs", "target": "actions_append_transcription_to_voice_doc", "relation": "contains", "confidence": "EXTRACTED", "source_file": "C:\\AI_knowledge_workspace\\Handy-main\\src-tauri\\src\\actions.rs", "source_location": "L469", "weight": 1.0}, {"source": "c_ai_knowledge_workspace_handy_main_src_tauri_src_actions_rs", "target": "actions_maybe_create_note_from_transcription", "relation": "contains", "confidence": "EXTRACTED", "source_file": "C:\\AI_knowledge_workspace\\Handy-main\\src-tauri\\src\\actions.rs", "source_location": "L528", "weight": 1.0}, {"source": "c_ai_knowledge_workspace_handy_main_src_tauri_src_actions_rs", "target": "actions_process_transcription_output", "relation": "contains", "confidence": "EXTRACTED", "source_file": "C:\\AI_knowledge_workspace\\Handy-main\\src-tauri\\src\\actions.rs", "source_location": "L724", "weight": 1.0}, {"source": "actions_transcribeaction", "target": "actions_transcribeaction_start", "relation": "method", "confidence": "EXTRACTED", "source_file": "C:\\AI_knowledge_workspace\\Handy-main\\src-tauri\\src\\actions.rs", "source_location": "L765", "weight": 1.0}, {"source": "actions_transcribeaction", "target": "actions_transcribeaction_stop", "relation": "method", "confidence": "EXTRACTED", "source_file": "C:\\AI_knowledge_workspace\\Handy-main\\src-tauri\\src\\actions.rs", "source_location": "L867", "weight": 1.0}, {"source": "c_ai_knowledge_workspace_handy_main_src_tauri_src_actions_rs", "target": "actions_cancelaction", "relation": "contains", "confidence": "EXTRACTED", "source_file": "C:\\AI_knowledge_workspace\\Handy-main\\src-tauri\\src\\actions.rs", "source_location": "L1059", "weight": 1.0}, {"source": "actions_cancelaction", "target": "actions_cancelaction_start", "relation": "method", "confidence": "EXTRACTED", "source_file": "C:\\AI_knowledge_workspace\\Handy-main\\src-tauri\\src\\actions.rs", "source_location": "L1062", "weight": 1.0}, {"source": "actions_cancelaction", "target": "actions_cancelaction_stop", "relation": "method", "confidence": "EXTRACTED", "source_file": "C:\\AI_knowledge_workspace\\Handy-main\\src-tauri\\src\\actions.rs", "source_location": "L1066", "weight": 1.0}, {"source": "c_ai_knowledge_workspace_handy_main_src_tauri_src_actions_rs", "target": "actions_testaction", "relation": "contains", "confidence": "EXTRACTED", "source_file": "C:\\AI_knowledge_workspace\\Handy-main\\src-tauri\\src\\actions.rs", "source_location": "L1072", "weight": 1.0}, {"source": "actions_testaction", "target": "actions_testaction_start", "relation": "method", "confidence": "EXTRACTED", "source_file": "C:\\AI_knowledge_workspace\\Handy-main\\src-tauri\\src\\actions.rs", "source_location": "L1075", "weight": 1.0}, {"source": "actions_testaction", "target": "actions_testaction_stop", "relation": "method", "confidence": "EXTRACTED", "source_file": "C:\\AI_knowledge_workspace\\Handy-main\\src-tauri\\src\\actions.rs", "source_location": "L1084", "weight": 1.0}, {"source": "c_ai_knowledge_workspace_handy_main_src_tauri_src_actions_rs", "target": "super", "relation": "imports_from", "confidence": "EXTRACTED", "source_file": "C:\\AI_knowledge_workspace\\Handy-main\\src-tauri\\src\\actions.rs", "source_location": "L1120", "weight": 1.0}, {"source": "c_ai_knowledge_workspace_handy_main_src_tauri_src_actions_rs", "target": "actions_create_markdown_note_content_returns_trimmed_text", "relation": "contains", "confidence": "EXTRACTED", "source_file": "C:\\AI_knowledge_workspace\\Handy-main\\src-tauri\\src\\actions.rs", "source_location": "L1123", "weight": 1.0}, {"source": "c_ai_knowledge_workspace_handy_main_src_tauri_src_actions_rs", "target": "actions_append_markdown_note_content_joins_with_blank_line", "relation": "contains", "confidence": "EXTRACTED", "source_file": "C:\\AI_knowledge_workspace\\Handy-main\\src-tauri\\src\\actions.rs", "source_location": "L1129", "weight": 1.0}, {"source": "actions_post_process_transcription", "target": "actions_build_system_prompt", "relation": "calls", "confidence": "EXTRACTED", "source_file": "C:\\AI_knowledge_workspace\\Handy-main\\src-tauri\\src\\actions.rs", "source_location": "L167", "weight": 1.0}, {"source": "actions_post_process_transcription", "target": "actions_strip_invisible_chars", "relation": "calls", "confidence": "EXTRACTED", "source_file": "C:\\AI_knowledge_workspace\\Handy-main\\src-tauri\\src\\actions.rs", "source_location": "L192", "weight": 1.0}, {"source": "actions_append_transcription_to_voice_doc", "target": "actions_voice_memo_recording_block", "relation": "calls", "confidence": "EXTRACTED", "source_file": "C:\\AI_knowledge_workspace\\Handy-main\\src-tauri\\src\\actions.rs", "source_location": "L477", "weight": 1.0}, {"source": "actions_append_transcription_to_voice_doc", "target": "actions_append_markdown_note_content", "relation": "calls", "confidence": "EXTRACTED", "source_file": "C:\\AI_knowledge_workspace\\Handy-main\\src-tauri\\src\\actions.rs", "source_location": "L480", "weight": 1.0}, {"source": "actions_maybe_create_note_from_transcription", "target": "actions_voice_memo_daily_title_for_local_date", "relation": "calls", "confidence": "EXTRACTED", "source_file": "C:\\AI_knowledge_workspace\\Handy-main\\src-tauri\\src\\actions.rs", "source_location": "L546", "weight": 1.0}, {"source": "actions_maybe_create_note_from_transcription", "target": "actions_legacy_voice_memo_daily_title_for_local_date", "relation": "calls", "confidence": "EXTRACTED", "source_file": "C:\\AI_knowledge_workspace\\Handy-main\\src-tauri\\src\\actions.rs", "source_location": "L547", "weight": 1.0}, {"source": "actions_maybe_create_note_from_transcription", "target": "actions_migrate_legacy_voice_memo_title", "relation": "calls", "confidence": "EXTRACTED", "source_file": "C:\\AI_knowledge_workspace\\Handy-main\\src-tauri\\src\\actions.rs", "source_location": "L559", "weight": 1.0}, {"source": "actions_maybe_create_note_from_transcription", "target": "actions_append_transcription_to_voice_doc", "relation": "calls", "confidence": "EXTRACTED", "source_file": "C:\\AI_knowledge_workspace\\Handy-main\\src-tauri\\src\\actions.rs", "source_location": "L569", "weight": 1.0}, {"source": "actions_maybe_create_note_from_transcription", "target": "actions_voice_memo_recording_block", "relation": "calls", "confidence": "EXTRACTED", "source_file": "C:\\AI_knowledge_workspace\\Handy-main\\src-tauri\\src\\actions.rs", "source_location": "L654", "weight": 1.0}, {"source": "actions_maybe_create_note_from_transcription", "target": "actions_create_markdown_note_content", "relation": "calls", "confidence": "EXTRACTED", "source_file": "C:\\AI_knowledge_workspace\\Handy-main\\src-tauri\\src\\actions.rs", "source_location": "L655", "weight": 1.0}, {"source": "actions_process_transcription_output", "target": "actions_maybe_convert_chinese_variant", "relation": "calls", "confidence": "EXTRACTED", "source_file": "C:\\AI_knowledge_workspace\\Handy-main\\src-tauri\\src\\actions.rs", "source_location": "L734", "weight": 1.0}, {"source": "actions_process_transcription_output", "target": "actions_post_process_transcription", "relation": "calls", "confidence": "EXTRACTED", "source_file": "C:\\AI_knowledge_workspace\\Handy-main\\src-tauri\\src\\actions.rs", "source_location": "L739", "weight": 1.0}, {"source": "actions_transcribeaction_stop", "target": "actions_finishguard", "relation": "calls", "confidence": "EXTRACTED", "source_file": "C:\\AI_knowledge_workspace\\Handy-main\\src-tauri\\src\\actions.rs", "source_location": "L892", "weight": 1.0}, {"source": "actions_transcribeaction_stop", "target": "actions_finalize_transcription_ui", "relation": "calls", "confidence": "EXTRACTED", "source_file": "C:\\AI_knowledge_workspace\\Handy-main\\src-tauri\\src\\actions.rs", "source_location": "L908", "weight": 1.0}, {"source": "actions_transcribeaction_stop", "target": "actions_process_transcription_output", "relation": "calls", "confidence": "EXTRACTED", "source_file": "C:\\AI_knowledge_workspace\\Handy-main\\src-tauri\\src\\actions.rs", "source_location": "L960", "weight": 1.0}, {"source": "actions_transcribeaction_stop", "target": "actions_maybe_create_note_from_transcription", "relation": "calls", "confidence": "EXTRACTED", "source_file": "C:\\AI_knowledge_workspace\\Handy-main\\src-tauri\\src\\actions.rs", "source_location": "L981", "weight": 1.0}, {"source": "actions_create_markdown_note_content_returns_trimmed_text", "target": "actions_create_markdown_note_content", "relation": "calls", "confidence": "EXTRACTED", "source_file": "C:\\AI_knowledge_workspace\\Handy-main\\src-tauri\\src\\actions.rs", "source_location": "L1124", "weight": 1.0}, {"source": "actions_append_markdown_note_content_joins_with_blank_line", "target": "actions_create_markdown_note_content", "relation": "calls", "confidence": "EXTRACTED", "source_file": "C:\\AI_knowledge_workspace\\Handy-main\\src-tauri\\src\\actions.rs", "source_location": "L1130", "weight": 1.0}, {"source": "actions_append_markdown_note_content_joins_with_blank_line", "target": "actions_append_markdown_note_content", "relation": "calls", "confidence": "EXTRACTED", "source_file": "C:\\AI_knowledge_workspace\\Handy-main\\src-tauri\\src\\actions.rs", "source_location": "L1131", "weight": 1.0}], "raw_calls": [{"caller_nid": "actions_finishguard_drop", "callee": "notify_processing_finished", "source_file": "C:\\AI_knowledge_workspace\\Handy-main\\src-tauri\\src\\actions.rs", "source_location": "L42"}, {"caller_nid": "actions_finalize_transcription_ui", "callee": "clone", "source_file": "C:\\AI_knowledge_workspace\\Handy-main\\src-tauri\\src\\actions.rs", "source_location": "L50"}, {"caller_nid": "actions_finalize_transcription_ui", "callee": "spawn", "source_file": "C:\\AI_knowledge_workspace\\Handy-main\\src-tauri\\src\\actions.rs", "source_location": "L51"}, {"caller_nid": "actions_finalize_transcription_ui", "callee": "finalize_active_voice_workspace_index", "source_file": "C:\\AI_knowledge_workspace\\Handy-main\\src-tauri\\src\\actions.rs", "source_location": "L52"}, {"caller_nid": "actions_finalize_transcription_ui", "callee": "clone", "source_file": "C:\\AI_knowledge_workspace\\Handy-main\\src-tauri\\src\\actions.rs", "source_location": "L57"}, {"caller_nid": "actions_finalize_transcription_ui", "callee": "clone", "source_file": "C:\\AI_knowledge_workspace\\Handy-main\\src-tauri\\src\\actions.rs", "source_location": "L58"}, {"caller_nid": "actions_finalize_transcription_ui", "callee": "run_on_main_thread", "source_file": "C:\\AI_knowledge_workspace\\Handy-main\\src-tauri\\src\\actions.rs", "source_location": "L59"}, {"caller_nid": "actions_finalize_transcription_ui", "callee": "hide_recording_overlay", "source_file": "C:\\AI_knowledge_workspace\\Handy-main\\src-tauri\\src\\actions.rs", "source_location": "L60"}, {"caller_nid": "actions_finalize_transcription_ui", "callee": "change_tray_icon", "source_file": "C:\\AI_knowledge_workspace\\Handy-main\\src-tauri\\src\\actions.rs", "source_location": "L61"}, {"caller_nid": "actions_finalize_transcription_ui", "callee": "hide_recording_overlay", "source_file": "C:\\AI_knowledge_workspace\\Handy-main\\src-tauri\\src\\actions.rs", "source_location": "L72"}, {"caller_nid": "actions_finalize_transcription_ui", "callee": "change_tray_icon", "source_file": "C:\\AI_knowledge_workspace\\Handy-main\\src-tauri\\src\\actions.rs", "source_location": "L73"}, {"caller_nid": "actions_strip_invisible_chars", "callee": "replace", "source_file": "C:\\AI_knowledge_workspace\\Handy-main\\src-tauri\\src\\actions.rs", "source_location": "L93"}, {"caller_nid": "actions_build_system_prompt", "callee": "to_string", "source_file": "C:\\AI_knowledge_workspace\\Handy-main\\src-tauri\\src\\actions.rs", "source_location": "L99"}, {"caller_nid": "actions_build_system_prompt", "callee": "trim", "source_file": "C:\\AI_knowledge_workspace\\Handy-main\\src-tauri\\src\\actions.rs", "source_location": "L99"}, {"caller_nid": "actions_build_system_prompt", "callee": "replace", "source_file": "C:\\AI_knowledge_workspace\\Handy-main\\src-tauri\\src\\actions.rs", "source_location": "L99"}, {"caller_nid": "actions_post_process_transcription", "callee": "cloned", "source_file": "C:\\AI_knowledge_workspace\\Handy-main\\src-tauri\\src\\actions.rs", "source_location": "L103"}, {"caller_nid": "actions_post_process_transcription", "callee": "active_post_process_provider", "source_file": "C:\\AI_knowledge_workspace\\Handy-main\\src-tauri\\src\\actions.rs", "source_location": "L103"}, {"caller_nid": "actions_post_process_transcription", "callee": "unwrap_or_default", "source_file": "C:\\AI_knowledge_workspace\\Handy-main\\src-tauri\\src\\actions.rs", "source_location": "L111"}, {"caller_nid": "actions_post_process_transcription", "callee": "cloned", "source_file": "C:\\AI_knowledge_workspace\\Handy-main\\src-tauri\\src\\actions.rs", "source_location": "L111"}, {"caller_nid": "actions_post_process_transcription", "callee": "get", "source_file": "C:\\AI_knowledge_workspace\\Handy-main\\src-tauri\\src\\actions.rs", "source_location": "L111"}, {"caller_nid": "actions_post_process_transcription", "callee": "is_empty", "source_file": "C:\\AI_knowledge_workspace\\Handy-main\\src-tauri\\src\\actions.rs", "source_location": "L117"}, {"caller_nid": "actions_post_process_transcription", "callee": "trim", "source_file": "C:\\AI_knowledge_workspace\\Handy-main\\src-tauri\\src\\actions.rs", "source_location": "L117"}, {"caller_nid": "actions_post_process_transcription", "callee": "clone", "source_file": "C:\\AI_knowledge_workspace\\Handy-main\\src-tauri\\src\\actions.rs", "source_location": "L126"}, {"caller_nid": "actions_post_process_transcription", "callee": "find", "source_file": "C:\\AI_knowledge_workspace\\Handy-main\\src-tauri\\src\\actions.rs", "source_location": "L133"}, {"caller_nid": "actions_post_process_transcription", "callee": "iter", "source_file": "C:\\AI_knowledge_workspace\\Handy-main\\src-tauri\\src\\actions.rs", "source_location": "L133"}, {"caller_nid": "actions_post_process_transcription", "callee": "clone", "source_file": "C:\\AI_knowledge_workspace\\Handy-main\\src-tauri\\src\\actions.rs", "source_location": "L138"}, {"caller_nid": "actions_post_process_transcription", "callee": "is_empty", "source_file": "C:\\AI_knowledge_workspace\\Handy-main\\src-tauri\\src\\actions.rs", "source_location": "L148"}, {"caller_nid": "actions_post_process_transcription", "callee": "trim", "source_file": "C:\\AI_knowledge_workspace\\Handy-main\\src-tauri\\src\\actions.rs", "source_location": "L148"}, {"caller_nid": "actions_post_process_transcription", "callee": "unwrap_or_default", "source_file": "C:\\AI_knowledge_workspace\\Handy-main\\src-tauri\\src\\actions.rs", "source_location": "L158"}, {"caller_nid": "actions_post_process_transcription", "callee": "cloned", "source_file": "C:\\AI_knowledge_workspace\\Handy-main\\src-tauri\\src\\actions.rs", "source_location": "L158"}, {"caller_nid": "actions_post_process_transcription", "callee": "get", "source_file": "C:\\AI_knowledge_workspace\\Handy-main\\src-tauri\\src\\actions.rs", "source_location": "L158"}, {"caller_nid": "actions_post_process_transcription", "callee": "to_string", "source_file": "C:\\AI_knowledge_workspace\\Handy-main\\src-tauri\\src\\actions.rs", "source_location": "L168"}, {"caller_nid": "actions_post_process_transcription", "callee": "check_apple_intelligence_availability", "source_file": "C:\\AI_knowledge_workspace\\Handy-main\\src-tauri\\src\\actions.rs", "source_location": "L174"}, {"caller_nid": "actions_post_process_transcription", "callee": "unwrap_or", "source_file": "C:\\AI_knowledge_workspace\\Handy-main\\src-tauri\\src\\actions.rs", "source_location": "L181"}, {"caller_nid": "actions_post_process_transcription", "callee": "trim", "source_file": "C:\\AI_knowledge_workspace\\Handy-main\\src-tauri\\src\\actions.rs", "source_location": "L181"}, {"caller_nid": "actions_post_process_transcription", "callee": "process_text_with_system_prompt", "source_file": "C:\\AI_knowledge_workspace\\Handy-main\\src-tauri\\src\\actions.rs", "source_location": "L182"}, {"caller_nid": "actions_post_process_transcription", "callee": "is_empty", "source_file": "C:\\AI_knowledge_workspace\\Handy-main\\src-tauri\\src\\actions.rs", "source_location": "L188"}, {"caller_nid": "actions_post_process_transcription", "callee": "trim", "source_file": "C:\\AI_knowledge_workspace\\Handy-main\\src-tauri\\src\\actions.rs", "source_location": "L188"}, {"caller_nid": "actions_post_process_transcription", "callee": "Some", "source_file": "C:\\AI_knowledge_workspace\\Handy-main\\src-tauri\\src\\actions.rs", "source_location": "L197"}, {"caller_nid": "actions_post_process_transcription", "callee": "send_chat_completion_with_schema", "source_file": "C:\\AI_knowledge_workspace\\Handy-main\\src-tauri\\src\\actions.rs", "source_location": "L227"}, {"caller_nid": "actions_post_process_transcription", "callee": "clone", "source_file": "C:\\AI_knowledge_workspace\\Handy-main\\src-tauri\\src\\actions.rs", "source_location": "L229"}, {"caller_nid": "actions_post_process_transcription", "callee": "Some", "source_file": "C:\\AI_knowledge_workspace\\Handy-main\\src-tauri\\src\\actions.rs", "source_location": "L232"}, {"caller_nid": "actions_post_process_transcription", "callee": "Some", "source_file": "C:\\AI_knowledge_workspace\\Handy-main\\src-tauri\\src\\actions.rs", "source_location": "L233"}, {"caller_nid": "actions_post_process_transcription", "callee": "Some", "source_file": "C:\\AI_knowledge_workspace\\Handy-main\\src-tauri\\src\\actions.rs", "source_location": "L234"}, {"caller_nid": "actions_post_process_transcription", "callee": "and_then", "source_file": "C:\\AI_knowledge_workspace\\Handy-main\\src-tauri\\src\\actions.rs", "source_location": "L243"}, {"caller_nid": "actions_post_process_transcription", "callee": "get", "source_file": "C:\\AI_knowledge_workspace\\Handy-main\\src-tauri\\src\\actions.rs", "source_location": "L243"}, {"caller_nid": "actions_post_process_transcription", "callee": "as_str", "source_file": "C:\\AI_knowledge_workspace\\Handy-main\\src-tauri\\src\\actions.rs", "source_location": "L243"}, {"caller_nid": "actions_post_process_transcription", "callee": "Some", "source_file": "C:\\AI_knowledge_workspace\\Handy-main\\src-tauri\\src\\actions.rs", "source_location": "L251"}, {"caller_nid": "actions_post_process_transcription", "callee": "Some", "source_file": "C:\\AI_knowledge_workspace\\Handy-main\\src-tauri\\src\\actions.rs", "source_location": "L254"}, {"caller_nid": "actions_post_process_transcription", "callee": "Some", "source_file": "C:\\AI_knowledge_workspace\\Handy-main\\src-tauri\\src\\actions.rs", "source_location": "L262"}, {"caller_nid": "actions_post_process_transcription", "callee": "replace", "source_file": "C:\\AI_knowledge_workspace\\Handy-main\\src-tauri\\src\\actions.rs", "source_location": "L281"}, {"caller_nid": "actions_post_process_transcription", "callee": "send_chat_completion", "source_file": "C:\\AI_knowledge_workspace\\Handy-main\\src-tauri\\src\\actions.rs", "source_location": "L284"}, {"caller_nid": "actions_post_process_transcription", "callee": "Some", "source_file": "C:\\AI_knowledge_workspace\\Handy-main\\src-tauri\\src\\actions.rs", "source_location": "L289"}, {"caller_nid": "actions_post_process_transcription", "callee": "Some", "source_file": "C:\\AI_knowledge_workspace\\Handy-main\\src-tauri\\src\\actions.rs", "source_location": "L300"}, {"caller_nid": "actions_maybe_convert_chinese_variant", "callee": "from_config", "source_file": "C:\\AI_knowledge_workspace\\Handy-main\\src-tauri\\src\\actions.rs", "source_location": "L344"}, {"caller_nid": "actions_maybe_convert_chinese_variant", "callee": "convert", "source_file": "C:\\AI_knowledge_workspace\\Handy-main\\src-tauri\\src\\actions.rs", "source_location": "L346"}, {"caller_nid": "actions_maybe_convert_chinese_variant", "callee": "Some", "source_file": "C:\\AI_knowledge_workspace\\Handy-main\\src-tauri\\src\\actions.rs", "source_location": "L352"}, {"caller_nid": "actions_voice_memo_daily_title_for_local_date", "callee": "date_naive", "source_file": "C:\\AI_knowledge_workspace\\Handy-main\\src-tauri\\src\\actions.rs", "source_location": "L369"}, {"caller_nid": "actions_voice_memo_daily_title_for_local_date", "callee": "now", "source_file": "C:\\AI_knowledge_workspace\\Handy-main\\src-tauri\\src\\actions.rs", "source_location": "L369"}, {"caller_nid": "actions_legacy_voice_memo_daily_title_for_local_date", "callee": "date_naive", "source_file": "C:\\AI_knowledge_workspace\\Handy-main\\src-tauri\\src\\actions.rs", "source_location": "L376"}, {"caller_nid": "actions_legacy_voice_memo_daily_title_for_local_date", "callee": "now", "source_file": "C:\\AI_knowledge_workspace\\Handy-main\\src-tauri\\src\\actions.rs", "source_location": "L376"}, {"caller_nid": "actions_migrate_legacy_voice_memo_title", "callee": "update_node", "source_file": "C:\\AI_knowledge_workspace\\Handy-main\\src-tauri\\src\\actions.rs", "source_location": "L396"}, {"caller_nid": "actions_migrate_legacy_voice_memo_title", "callee": "clone", "source_file": "C:\\AI_knowledge_workspace\\Handy-main\\src-tauri\\src\\actions.rs", "source_location": "L401"}, {"caller_nid": "actions_migrate_legacy_voice_memo_title", "callee": "write_node_to_vault", "source_file": "C:\\AI_knowledge_workspace\\Handy-main\\src-tauri\\src\\actions.rs", "source_location": "L402"}, {"caller_nid": "actions_migrate_legacy_voice_memo_title", "callee": "as_deref", "source_file": "C:\\AI_knowledge_workspace\\Handy-main\\src-tauri\\src\\actions.rs", "source_location": "L407"}, {"caller_nid": "actions_migrate_legacy_voice_memo_title", "callee": "join", "source_file": "C:\\AI_knowledge_workspace\\Handy-main\\src-tauri\\src\\actions.rs", "source_location": "L409"}, {"caller_nid": "actions_migrate_legacy_voice_memo_title", "callee": "resolve_vault_root", "source_file": "C:\\AI_knowledge_workspace\\Handy-main\\src-tauri\\src\\actions.rs", "source_location": "L409"}, {"caller_nid": "actions_migrate_legacy_voice_memo_title", "callee": "exists", "source_file": "C:\\AI_knowledge_workspace\\Handy-main\\src-tauri\\src\\actions.rs", "source_location": "L410"}, {"caller_nid": "actions_migrate_legacy_voice_memo_title", "callee": "remove_file", "source_file": "C:\\AI_knowledge_workspace\\Handy-main\\src-tauri\\src\\actions.rs", "source_location": "L411"}, {"caller_nid": "actions_migrate_legacy_voice_memo_title", "callee": "update_vault_rel_path", "source_file": "C:\\AI_knowledge_workspace\\Handy-main\\src-tauri\\src\\actions.rs", "source_location": "L421"}, {"caller_nid": "actions_migrate_legacy_voice_memo_title", "callee": "Ok", "source_file": "C:\\AI_knowledge_workspace\\Handy-main\\src-tauri\\src\\actions.rs", "source_location": "L432"}, {"caller_nid": "actions_create_markdown_note_content", "callee": "to_string", "source_file": "C:\\AI_knowledge_workspace\\Handy-main\\src-tauri\\src\\actions.rs", "source_location": "L436"}, {"caller_nid": "actions_create_markdown_note_content", "callee": "trim", "source_file": "C:\\AI_knowledge_workspace\\Handy-main\\src-tauri\\src\\actions.rs", "source_location": "L436"}, {"caller_nid": "actions_append_markdown_note_content", "callee": "trim", "source_file": "C:\\AI_knowledge_workspace\\Handy-main\\src-tauri\\src\\actions.rs", "source_location": "L440"}, {"caller_nid": "actions_append_markdown_note_content", "callee": "trim", "source_file": "C:\\AI_knowledge_workspace\\Handy-main\\src-tauri\\src\\actions.rs", "source_location": "L441"}, {"caller_nid": "actions_append_markdown_note_content", "callee": "is_empty", "source_file": "C:\\AI_knowledge_workspace\\Handy-main\\src-tauri\\src\\actions.rs", "source_location": "L442"}, {"caller_nid": "actions_append_markdown_note_content", "callee": "to_string", "source_file": "C:\\AI_knowledge_workspace\\Handy-main\\src-tauri\\src\\actions.rs", "source_location": "L443"}, {"caller_nid": "actions_append_markdown_note_content", "callee": "is_empty", "source_file": "C:\\AI_knowledge_workspace\\Handy-main\\src-tauri\\src\\actions.rs", "source_location": "L445"}, {"caller_nid": "actions_append_markdown_note_content", "callee": "to_string", "source_file": "C:\\AI_knowledge_workspace\\Handy-main\\src-tauri\\src\\actions.rs", "source_location": "L446"}, {"caller_nid": "actions_directive_escape_path", "callee": "replace", "source_file": "C:\\AI_knowledge_workspace\\Handy-main\\src-tauri\\src\\actions.rs", "source_location": "L452"}, {"caller_nid": "actions_directive_escape_path", "callee": "replace", "source_file": "C:\\AI_knowledge_workspace\\Handy-main\\src-tauri\\src\\actions.rs", "source_location": "L452"}, {"caller_nid": "actions_append_transcription_to_voice_doc", "callee": "as_ref", "source_file": "C:\\AI_knowledge_workspace\\Handy-main\\src-tauri\\src\\actions.rs", "source_location": "L476"}, {"caller_nid": "actions_append_transcription_to_voice_doc", "callee": "is_empty", "source_file": "C:\\AI_knowledge_workspace\\Handy-main\\src-tauri\\src\\actions.rs", "source_location": "L477"}, {"caller_nid": "actions_append_transcription_to_voice_doc", "callee": "trim", "source_file": "C:\\AI_knowledge_workspace\\Handy-main\\src-tauri\\src\\actions.rs", "source_location": "L477"}, {"caller_nid": "actions_append_transcription_to_voice_doc", "callee": "to_string", "source_file": "C:\\AI_knowledge_workspace\\Handy-main\\src-tauri\\src\\actions.rs", "source_location": "L478"}, {"caller_nid": "actions_append_transcription_to_voice_doc", "callee": "trim", "source_file": "C:\\AI_knowledge_workspace\\Handy-main\\src-tauri\\src\\actions.rs", "source_location": "L478"}, {"caller_nid": "actions_append_transcription_to_voice_doc", "callee": "as_str", "source_file": "C:\\AI_knowledge_workspace\\Handy-main\\src-tauri\\src\\actions.rs", "source_location": "L480"}, {"caller_nid": "actions_append_transcription_to_voice_doc", "callee": "update_node_body_persist_only", "source_file": "C:\\AI_knowledge_workspace\\Handy-main\\src-tauri\\src\\actions.rs", "source_location": "L482"}, {"caller_nid": "actions_append_transcription_to_voice_doc", "callee": "is_empty", "source_file": "C:\\AI_knowledge_workspace\\Handy-main\\src-tauri\\src\\actions.rs", "source_location": "L489"}, {"caller_nid": "actions_append_transcription_to_voice_doc", "callee": "trim", "source_file": "C:\\AI_knowledge_workspace\\Handy-main\\src-tauri\\src\\actions.rs", "source_location": "L489"}, {"caller_nid": "actions_append_transcription_to_voice_doc", "callee": "update_voice_memo_mirror_audio_path", "source_file": "C:\\AI_knowledge_workspace\\Handy-main\\src-tauri\\src\\actions.rs", "source_location": "L490"}, {"caller_nid": "actions_append_transcription_to_voice_doc", "callee": "Some", "source_file": "C:\\AI_knowledge_workspace\\Handy-main\\src-tauri\\src\\actions.rs", "source_location": "L492"}, {"caller_nid": "actions_append_transcription_to_voice_doc", "callee": "as_str", "source_file": "C:\\AI_knowledge_workspace\\Handy-main\\src-tauri\\src\\actions.rs", "source_location": "L492"}, {"caller_nid": "actions_append_transcription_to_voice_doc", "callee": "write_node_to_vault", "source_file": "C:\\AI_knowledge_workspace\\Handy-main\\src-tauri\\src\\actions.rs", "source_location": "L499"}, {"caller_nid": "actions_append_transcription_to_voice_doc", "callee": "update_vault_rel_path", "source_file": "C:\\AI_knowledge_workspace\\Handy-main\\src-tauri\\src\\actions.rs", "source_location": "L501"}, {"caller_nid": "actions_append_transcription_to_voice_doc", "callee": "emit_workspace_node_body_updated_throttled", "source_file": "C:\\AI_knowledge_workspace\\Handy-main\\src-tauri\\src\\actions.rs", "source_location": "L509"}, {"caller_nid": "actions_maybe_create_note_from_transcription", "callee": "get_settings", "source_file": "C:\\AI_knowledge_workspace\\Handy-main\\src-tauri\\src\\actions.rs", "source_location": "L533"}, {"caller_nid": "actions_maybe_create_note_from_transcription", "callee": "get_workspace_doc_id", "source_file": "C:\\AI_knowledge_workspace\\Handy-main\\src-tauri\\src\\actions.rs", "source_location": "L550"}, {"caller_nid": "actions_maybe_create_note_from_transcription", "callee": "get_node", "source_file": "C:\\AI_knowledge_workspace\\Handy-main\\src-tauri\\src\\actions.rs", "source_location": "L551"}, {"caller_nid": "actions_maybe_create_note_from_transcription", "callee": "is_none", "source_file": "C:\\AI_knowledge_workspace\\Handy-main\\src-tauri\\src\\actions.rs", "source_location": "L553"}, {"caller_nid": "actions_maybe_create_note_from_transcription", "callee": "as_ref", "source_file": "C:\\AI_knowledge_workspace\\Handy-main\\src-tauri\\src\\actions.rs", "source_location": "L559"}, {"caller_nid": "actions_maybe_create_note_from_transcription", "callee": "as_ref", "source_file": "C:\\AI_knowledge_workspace\\Handy-main\\src-tauri\\src\\actions.rs", "source_location": "L571"}, {"caller_nid": "actions_maybe_create_note_from_transcription", "callee": "finalize_voice_workspace_mirror", "source_file": "C:\\AI_knowledge_workspace\\Handy-main\\src-tauri\\src\\actions.rs", "source_location": "L581"}, {"caller_nid": "actions_maybe_create_note_from_transcription", "callee": "clear", "source_file": "C:\\AI_knowledge_workspace\\Handy-main\\src-tauri\\src\\actions.rs", "source_location": "L582"}, {"caller_nid": "actions_maybe_create_note_from_transcription", "callee": "ensure_transcription_folder", "source_file": "C:\\AI_knowledge_workspace\\Handy-main\\src-tauri\\src\\actions.rs", "source_location": "L589"}, {"caller_nid": "actions_maybe_create_note_from_transcription", "callee": "get_node_children", "source_file": "C:\\AI_knowledge_workspace\\Handy-main\\src-tauri\\src\\actions.rs", "source_location": "L601"}, {"caller_nid": "actions_maybe_create_note_from_transcription", "callee": "is_some", "source_file": "C:\\AI_knowledge_workspace\\Handy-main\\src-tauri\\src\\actions.rs", "source_location": "L613"}, {"caller_nid": "actions_maybe_create_note_from_transcription", "callee": "is_none", "source_file": "C:\\AI_knowledge_workspace\\Handy-main\\src-tauri\\src\\actions.rs", "source_location": "L616"}, {"caller_nid": "actions_maybe_create_note_from_transcription", "callee": "Some", "source_file": "C:\\AI_knowledge_workspace\\Handy-main\\src-tauri\\src\\actions.rs", "source_location": "L617"}, {"caller_nid": "actions_maybe_create_note_from_transcription", "callee": "is_none", "source_file": "C:\\AI_knowledge_workspace\\Handy-main\\src-tauri\\src\\actions.rs", "source_location": "L618"}, {"caller_nid": "actions_maybe_create_note_from_transcription", "callee": "Some", "source_file": "C:\\AI_knowledge_workspace\\Handy-main\\src-tauri\\src\\actions.rs", "source_location": "L619"}, {"caller_nid": "actions_maybe_create_note_from_transcription", "callee": "or", "source_file": "C:\\AI_knowledge_workspace\\Handy-main\\src-tauri\\src\\actions.rs", "source_location": "L622"}, {"caller_nid": "actions_maybe_create_note_from_transcription", "callee": "as_ref", "source_file": "C:\\AI_knowledge_workspace\\Handy-main\\src-tauri\\src\\actions.rs", "source_location": "L630"}, {"caller_nid": "actions_maybe_create_note_from_transcription", "callee": "set_workspace_doc_id", "source_file": "C:\\AI_knowledge_workspace\\Handy-main\\src-tauri\\src\\actions.rs", "source_location": "L640"}, {"caller_nid": "actions_maybe_create_note_from_transcription", "callee": "Some", "source_file": "C:\\AI_knowledge_workspace\\Handy-main\\src-tauri\\src\\actions.rs", "source_location": "L640"}, {"caller_nid": "actions_maybe_create_note_from_transcription", "callee": "clone", "source_file": "C:\\AI_knowledge_workspace\\Handy-main\\src-tauri\\src\\actions.rs", "source_location": "L640"}, {"caller_nid": "actions_maybe_create_note_from_transcription", "callee": "as_ref", "source_file": "C:\\AI_knowledge_workspace\\Handy-main\\src-tauri\\src\\actions.rs", "source_location": "L643"}, {"caller_nid": "actions_maybe_create_note_from_transcription", "callee": "as_ref", "source_file": "C:\\AI_knowledge_workspace\\Handy-main\\src-tauri\\src\\actions.rs", "source_location": "L653"}, {"caller_nid": "actions_maybe_create_note_from_transcription", "callee": "is_empty", "source_file": "C:\\AI_knowledge_workspace\\Handy-main\\src-tauri\\src\\actions.rs", "source_location": "L654"}, {"caller_nid": "actions_maybe_create_note_from_transcription", "callee": "trim", "source_file": "C:\\AI_knowledge_workspace\\Handy-main\\src-tauri\\src\\actions.rs", "source_location": "L654"}, {"caller_nid": "actions_maybe_create_note_from_transcription", "callee": "timestamp_millis", "source_file": "C:\\AI_knowledge_workspace\\Handy-main\\src-tauri\\src\\actions.rs", "source_location": "L657"}, {"caller_nid": "actions_maybe_create_note_from_transcription", "callee": "now", "source_file": "C:\\AI_knowledge_workspace\\Handy-main\\src-tauri\\src\\actions.rs", "source_location": "L657"}, {"caller_nid": "actions_maybe_create_note_from_transcription", "callee": "as_ref", "source_file": "C:\\AI_knowledge_workspace\\Handy-main\\src-tauri\\src\\actions.rs", "source_location": "L658"}, {"caller_nid": "actions_maybe_create_note_from_transcription", "callee": "is_empty", "source_file": "C:\\AI_knowledge_workspace\\Handy-main\\src-tauri\\src\\actions.rs", "source_location": "L659"}, {"caller_nid": "actions_maybe_create_note_from_transcription", "callee": "trim", "source_file": "C:\\AI_knowledge_workspace\\Handy-main\\src-tauri\\src\\actions.rs", "source_location": "L659"}, {"caller_nid": "actions_maybe_create_note_from_transcription", "callee": "to_string", "source_file": "C:\\AI_knowledge_workspace\\Handy-main\\src-tauri\\src\\actions.rs", "source_location": "L665"}, {"caller_nid": "actions_maybe_create_note_from_transcription", "callee": "create_document_child_with_properties", "source_file": "C:\\AI_knowledge_workspace\\Handy-main\\src-tauri\\src\\actions.rs", "source_location": "L674"}, {"caller_nid": "actions_maybe_create_note_from_transcription", "callee": "to_string", "source_file": "C:\\AI_knowledge_workspace\\Handy-main\\src-tauri\\src\\actions.rs", "source_location": "L694"}, {"caller_nid": "actions_maybe_create_note_from_transcription", "callee": "update_node_properties", "source_file": "C:\\AI_knowledge_workspace\\Handy-main\\src-tauri\\src\\actions.rs", "source_location": "L702"}, {"caller_nid": "actions_maybe_create_note_from_transcription", "callee": "write_node_to_vault", "source_file": "C:\\AI_knowledge_workspace\\Handy-main\\src-tauri\\src\\actions.rs", "source_location": "L710"}, {"caller_nid": "actions_maybe_create_note_from_transcription", "callee": "update_vault_rel_path", "source_file": "C:\\AI_knowledge_workspace\\Handy-main\\src-tauri\\src\\actions.rs", "source_location": "L712"}, {"caller_nid": "actions_maybe_create_note_from_transcription", "callee": "set_workspace_doc_id", "source_file": "C:\\AI_knowledge_workspace\\Handy-main\\src-tauri\\src\\actions.rs", "source_location": "L720"}, {"caller_nid": "actions_maybe_create_note_from_transcription", "callee": "Some", "source_file": "C:\\AI_knowledge_workspace\\Handy-main\\src-tauri\\src\\actions.rs", "source_location": "L720"}, {"caller_nid": "actions_maybe_create_note_from_transcription", "callee": "clone", "source_file": "C:\\AI_knowledge_workspace\\Handy-main\\src-tauri\\src\\actions.rs", "source_location": "L720"}, {"caller_nid": "actions_maybe_create_note_from_transcription", "callee": "emit_workspace_transcription_synced", "source_file": "C:\\AI_knowledge_workspace\\Handy-main\\src-tauri\\src\\actions.rs", "source_location": "L721"}, {"caller_nid": "actions_process_transcription_output", "callee": "get_settings", "source_file": "C:\\AI_knowledge_workspace\\Handy-main\\src-tauri\\src\\actions.rs", "source_location": "L729"}, {"caller_nid": "actions_process_transcription_output", "callee": "to_string", "source_file": "C:\\AI_knowledge_workspace\\Handy-main\\src-tauri\\src\\actions.rs", "source_location": "L730"}, {"caller_nid": "actions_process_transcription_output", "callee": "Some", "source_file": "C:\\AI_knowledge_workspace\\Handy-main\\src-tauri\\src\\actions.rs", "source_location": "L740"}, {"caller_nid": "actions_process_transcription_output", "callee": "clone", "source_file": "C:\\AI_knowledge_workspace\\Handy-main\\src-tauri\\src\\actions.rs", "source_location": "L740"}, {"caller_nid": "actions_process_transcription_output", "callee": "find", "source_file": "C:\\AI_knowledge_workspace\\Handy-main\\src-tauri\\src\\actions.rs", "source_location": "L744"}, {"caller_nid": "actions_process_transcription_output", "callee": "iter", "source_file": "C:\\AI_knowledge_workspace\\Handy-main\\src-tauri\\src\\actions.rs", "source_location": "L744"}, {"caller_nid": "actions_process_transcription_output", "callee": "Some", "source_file": "C:\\AI_knowledge_workspace\\Handy-main\\src-tauri\\src\\actions.rs", "source_location": "L749"}, {"caller_nid": "actions_process_transcription_output", "callee": "clone", "source_file": "C:\\AI_knowledge_workspace\\Handy-main\\src-tauri\\src\\actions.rs", "source_location": "L749"}, {"caller_nid": "actions_process_transcription_output", "callee": "Some", "source_file": "C:\\AI_knowledge_workspace\\Handy-main\\src-tauri\\src\\actions.rs", "source_location": "L754"}, {"caller_nid": "actions_process_transcription_output", "callee": "clone", "source_file": "C:\\AI_knowledge_workspace\\Handy-main\\src-tauri\\src\\actions.rs", "source_location": "L754"}, {"caller_nid": "actions_transcribeaction_start", "callee": "now", "source_file": "C:\\AI_knowledge_workspace\\Handy-main\\src-tauri\\src\\actions.rs", "source_location": "L766"}, {"caller_nid": "actions_transcribeaction_start", "callee": "initiate_model_load", "source_file": "C:\\AI_knowledge_workspace\\Handy-main\\src-tauri\\src\\actions.rs", "source_location": "L774"}, {"caller_nid": "actions_transcribeaction_start", "callee": "clone", "source_file": "C:\\AI_knowledge_workspace\\Handy-main\\src-tauri\\src\\actions.rs", "source_location": "L775"}, {"caller_nid": "actions_transcribeaction_start", "callee": "spawn", "source_file": "C:\\AI_knowledge_workspace\\Handy-main\\src-tauri\\src\\actions.rs", "source_location": "L776"}, {"caller_nid": "actions_transcribeaction_start", "callee": "preload_vad", "source_file": "C:\\AI_knowledge_workspace\\Handy-main\\src-tauri\\src\\actions.rs", "source_location": "L777"}, {"caller_nid": "actions_transcribeaction_start", "callee": "to_string", "source_file": "C:\\AI_knowledge_workspace\\Handy-main\\src-tauri\\src\\actions.rs", "source_location": "L782"}, {"caller_nid": "actions_transcribeaction_start", "callee": "change_tray_icon", "source_file": "C:\\AI_knowledge_workspace\\Handy-main\\src-tauri\\src\\actions.rs", "source_location": "L783"}, {"caller_nid": "actions_transcribeaction_start", "callee": "show_recording_overlay", "source_file": "C:\\AI_knowledge_workspace\\Handy-main\\src-tauri\\src\\actions.rs", "source_location": "L784"}, {"caller_nid": "actions_transcribeaction_start", "callee": "get_settings", "source_file": "C:\\AI_knowledge_workspace\\Handy-main\\src-tauri\\src\\actions.rs", "source_location": "L787"}, {"caller_nid": "actions_transcribeaction_start", "callee": "clone", "source_file": "C:\\AI_knowledge_workspace\\Handy-main\\src-tauri\\src\\actions.rs", "source_location": "L795"}, {"caller_nid": "actions_transcribeaction_start", "callee": "clone", "source_file": "C:\\AI_knowledge_workspace\\Handy-main\\src-tauri\\src\\actions.rs", "source_location": "L796"}, {"caller_nid": "actions_transcribeaction_start", "callee": "spawn", "source_file": "C:\\AI_knowledge_workspace\\Handy-main\\src-tauri\\src\\actions.rs", "source_location": "L799"}, {"caller_nid": "actions_transcribeaction_start", "callee": "play_feedback_sound_blocking", "source_file": "C:\\AI_knowledge_workspace\\Handy-main\\src-tauri\\src\\actions.rs", "source_location": "L800"}, {"caller_nid": "actions_transcribeaction_start", "callee": "apply_mute", "source_file": "C:\\AI_knowledge_workspace\\Handy-main\\src-tauri\\src\\actions.rs", "source_location": "L801"}, {"caller_nid": "actions_transcribeaction_start", "callee": "try_start_recording", "source_file": "C:\\AI_knowledge_workspace\\Handy-main\\src-tauri\\src\\actions.rs", "source_location": "L804"}, {"caller_nid": "actions_transcribeaction_start", "callee": "Some", "source_file": "C:\\AI_knowledge_workspace\\Handy-main\\src-tauri\\src\\actions.rs", "source_location": "L806"}, {"caller_nid": "actions_transcribeaction_start", "callee": "now", "source_file": "C:\\AI_knowledge_workspace\\Handy-main\\src-tauri\\src\\actions.rs", "source_location": "L812"}, {"caller_nid": "actions_transcribeaction_start", "callee": "try_start_recording", "source_file": "C:\\AI_knowledge_workspace\\Handy-main\\src-tauri\\src\\actions.rs", "source_location": "L813"}, {"caller_nid": "actions_transcribeaction_start", "callee": "clone", "source_file": "C:\\AI_knowledge_workspace\\Handy-main\\src-tauri\\src\\actions.rs", "source_location": "L817"}, {"caller_nid": "actions_transcribeaction_start", "callee": "clone", "source_file": "C:\\AI_knowledge_workspace\\Handy-main\\src-tauri\\src\\actions.rs", "source_location": "L818"}, {"caller_nid": "actions_transcribeaction_start", "callee": "spawn", "source_file": "C:\\AI_knowledge_workspace\\Handy-main\\src-tauri\\src\\actions.rs", "source_location": "L819"}, {"caller_nid": "actions_transcribeaction_start", "callee": "sleep", "source_file": "C:\\AI_knowledge_workspace\\Handy-main\\src-tauri\\src\\actions.rs", "source_location": "L820"}, {"caller_nid": "actions_transcribeaction_start", "callee": "from_millis", "source_file": "C:\\AI_knowledge_workspace\\Handy-main\\src-tauri\\src\\actions.rs", "source_location": "L820"}, {"caller_nid": "actions_transcribeaction_start", "callee": "play_feedback_sound_blocking", "source_file": "C:\\AI_knowledge_workspace\\Handy-main\\src-tauri\\src\\actions.rs", "source_location": "L824"}, {"caller_nid": "actions_transcribeaction_start", "callee": "apply_mute", "source_file": "C:\\AI_knowledge_workspace\\Handy-main\\src-tauri\\src\\actions.rs", "source_location": "L825"}, {"caller_nid": "actions_transcribeaction_start", "callee": "Some", "source_file": "C:\\AI_knowledge_workspace\\Handy-main\\src-tauri\\src\\actions.rs", "source_location": "L830"}, {"caller_nid": "actions_transcribeaction_start", "callee": "is_none", "source_file": "C:\\AI_knowledge_workspace\\Handy-main\\src-tauri\\src\\actions.rs", "source_location": "L835"}, {"caller_nid": "actions_transcribeaction_start", "callee": "register_cancel_shortcut", "source_file": "C:\\AI_knowledge_workspace\\Handy-main\\src-tauri\\src\\actions.rs", "source_location": "L837"}, {"caller_nid": "actions_transcribeaction_start", "callee": "hide_recording_overlay", "source_file": "C:\\AI_knowledge_workspace\\Handy-main\\src-tauri\\src\\actions.rs", "source_location": "L841"}, {"caller_nid": "actions_transcribeaction_start", "callee": "change_tray_icon", "source_file": "C:\\AI_knowledge_workspace\\Handy-main\\src-tauri\\src\\actions.rs", "source_location": "L842"}, {"caller_nid": "actions_transcribeaction_start", "callee": "is_microphone_access_denied", "source_file": "C:\\AI_knowledge_workspace\\Handy-main\\src-tauri\\src\\actions.rs", "source_location": "L844"}, {"caller_nid": "actions_transcribeaction_start", "callee": "is_no_input_device_error", "source_file": "C:\\AI_knowledge_workspace\\Handy-main\\src-tauri\\src\\actions.rs", "source_location": "L846"}, {"caller_nid": "actions_transcribeaction_start", "callee": "emit", "source_file": "C:\\AI_knowledge_workspace\\Handy-main\\src-tauri\\src\\actions.rs", "source_location": "L851"}, {"caller_nid": "actions_transcribeaction_start", "callee": "to_string", "source_file": "C:\\AI_knowledge_workspace\\Handy-main\\src-tauri\\src\\actions.rs", "source_location": "L854"}, {"caller_nid": "actions_transcribeaction_start", "callee": "Some", "source_file": "C:\\AI_knowledge_workspace\\Handy-main\\src-tauri\\src\\actions.rs", "source_location": "L855"}, {"caller_nid": "actions_transcribeaction_stop", "callee": "unregister_cancel_shortcut", "source_file": "C:\\AI_knowledge_workspace\\Handy-main\\src-tauri\\src\\actions.rs", "source_location": "L869"}, {"caller_nid": "actions_transcribeaction_stop", "callee": "now", "source_file": "C:\\AI_knowledge_workspace\\Handy-main\\src-tauri\\src\\actions.rs", "source_location": "L871"}, {"caller_nid": "actions_transcribeaction_stop", "callee": "clone", "source_file": "C:\\AI_knowledge_workspace\\Handy-main\\src-tauri\\src\\actions.rs", "source_location": "L874"}, {"caller_nid": "actions_transcribeaction_stop", "callee": "clone", "source_file": "C:\\AI_knowledge_workspace\\Handy-main\\src-tauri\\src\\actions.rs", "source_location": "L875"}, {"caller_nid": "actions_transcribeaction_stop", "callee": "clone", "source_file": "C:\\AI_knowledge_workspace\\Handy-main\\src-tauri\\src\\actions.rs", "source_location": "L876"}, {"caller_nid": "actions_transcribeaction_stop", "callee": "clone", "source_file": "C:\\AI_knowledge_workspace\\Handy-main\\src-tauri\\src\\actions.rs", "source_location": "L877"}, {"caller_nid": "actions_transcribeaction_stop", "callee": "change_tray_icon", "source_file": "C:\\AI_knowledge_workspace\\Handy-main\\src-tauri\\src\\actions.rs", "source_location": "L879"}, {"caller_nid": "actions_transcribeaction_stop", "callee": "show_transcribing_overlay", "source_file": "C:\\AI_knowledge_workspace\\Handy-main\\src-tauri\\src\\actions.rs", "source_location": "L880"}, {"caller_nid": "actions_transcribeaction_stop", "callee": "remove_mute", "source_file": "C:\\AI_knowledge_workspace\\Handy-main\\src-tauri\\src\\actions.rs", "source_location": "L883"}, {"caller_nid": "actions_transcribeaction_stop", "callee": "play_feedback_sound", "source_file": "C:\\AI_knowledge_workspace\\Handy-main\\src-tauri\\src\\actions.rs", "source_location": "L886"}, {"caller_nid": "actions_transcribeaction_stop", "callee": "to_string", "source_file": "C:\\AI_knowledge_workspace\\Handy-main\\src-tauri\\src\\actions.rs", "source_location": "L888"}, {"caller_nid": "actions_transcribeaction_stop", "callee": "spawn", "source_file": "C:\\AI_knowledge_workspace\\Handy-main\\src-tauri\\src\\actions.rs", "source_location": "L891"}, {"caller_nid": "actions_transcribeaction_stop", "callee": "clone", "source_file": "C:\\AI_knowledge_workspace\\Handy-main\\src-tauri\\src\\actions.rs", "source_location": "L892"}, {"caller_nid": "actions_transcribeaction_stop", "callee": "now", "source_file": "C:\\AI_knowledge_workspace\\Handy-main\\src-tauri\\src\\actions.rs", "source_location": "L898"}, {"caller_nid": "actions_transcribeaction_stop", "callee": "stop_recording", "source_file": "C:\\AI_knowledge_workspace\\Handy-main\\src-tauri\\src\\actions.rs", "source_location": "L899"}, {"caller_nid": "actions_transcribeaction_stop", "callee": "is_empty", "source_file": "C:\\AI_knowledge_workspace\\Handy-main\\src-tauri\\src\\actions.rs", "source_location": "L906"}, {"caller_nid": "actions_transcribeaction_stop", "callee": "len", "source_file": "C:\\AI_knowledge_workspace\\Handy-main\\src-tauri\\src\\actions.rs", "source_location": "L911"}, {"caller_nid": "actions_transcribeaction_stop", "callee": "join", "source_file": "C:\\AI_knowledge_workspace\\Handy-main\\src-tauri\\src\\actions.rs", "source_location": "L913"}, {"caller_nid": "actions_transcribeaction_stop", "callee": "recordings_dir", "source_file": "C:\\AI_knowledge_workspace\\Handy-main\\src-tauri\\src\\actions.rs", "source_location": "L913"}, {"caller_nid": "actions_transcribeaction_stop", "callee": "clone", "source_file": "C:\\AI_knowledge_workspace\\Handy-main\\src-tauri\\src\\actions.rs", "source_location": "L914"}, {"caller_nid": "actions_transcribeaction_stop", "callee": "clone", "source_file": "C:\\AI_knowledge_workspace\\Handy-main\\src-tauri\\src\\actions.rs", "source_location": "L915"}, {"caller_nid": "actions_transcribeaction_stop", "callee": "spawn_blocking", "source_file": "C:\\AI_knowledge_workspace\\Handy-main\\src-tauri\\src\\actions.rs", "source_location": "L916"}, {"caller_nid": "actions_transcribeaction_stop", "callee": "save_wav_file", "source_file": "C:\\AI_knowledge_workspace\\Handy-main\\src-tauri\\src\\actions.rs", "source_location": "L917"}, {"caller_nid": "actions_transcribeaction_stop", "callee": "now", "source_file": "C:\\AI_knowledge_workspace\\Handy-main\\src-tauri\\src\\actions.rs", "source_location": "L921"}, {"caller_nid": "actions_transcribeaction_stop", "callee": "transcribe", "source_file": "C:\\AI_knowledge_workspace\\Handy-main\\src-tauri\\src\\actions.rs", "source_location": "L922"}, {"caller_nid": "actions_transcribeaction_stop", "callee": "verify_wav_file", "source_file": "C:\\AI_knowledge_workspace\\Handy-main\\src-tauri\\src\\actions.rs", "source_location": "L927"}, {"caller_nid": "actions_transcribeaction_stop", "callee": "show_processing_overlay", "source_file": "C:\\AI_knowledge_workspace\\Handy-main\\src-tauri\\src\\actions.rs", "source_location": "L957"}, {"caller_nid": "actions_transcribeaction_stop", "callee": "save_entry", "source_file": "C:\\AI_knowledge_workspace\\Handy-main\\src-tauri\\src\\actions.rs", "source_location": "L965"}, {"caller_nid": "actions_transcribeaction_stop", "callee": "clone", "source_file": "C:\\AI_knowledge_workspace\\Handy-main\\src-tauri\\src\\actions.rs", "source_location": "L967"}, {"caller_nid": "actions_transcribeaction_stop", "callee": "clone", "source_file": "C:\\AI_knowledge_workspace\\Handy-main\\src-tauri\\src\\actions.rs", "source_location": "L969"}, {"caller_nid": "actions_transcribeaction_stop", "callee": "clone", "source_file": "C:\\AI_knowledge_workspace\\Handy-main\\src-tauri\\src\\actions.rs", "source_location": "L970"}, {"caller_nid": "actions_transcribeaction_stop", "callee": "Some", "source_file": "C:\\AI_knowledge_workspace\\Handy-main\\src-tauri\\src\\actions.rs", "source_location": "L977"}, {"caller_nid": "actions_transcribeaction_stop", "callee": "to_string", "source_file": "C:\\AI_knowledge_workspace\\Handy-main\\src-tauri\\src\\actions.rs", "source_location": "L977"}, {"caller_nid": "actions_transcribeaction_stop", "callee": "to_string_lossy", "source_file": "C:\\AI_knowledge_workspace\\Handy-main\\src-tauri\\src\\actions.rs", "source_location": "L977"}, {"caller_nid": "actions_transcribeaction_stop", "callee": "is_empty", "source_file": "C:\\AI_knowledge_workspace\\Handy-main\\src-tauri\\src\\actions.rs", "source_location": "L988"}, {"caller_nid": "actions_transcribeaction_stop", "callee": "get_settings", "source_file": "C:\\AI_knowledge_workspace\\Handy-main\\src-tauri\\src\\actions.rs", "source_location": "L991"}, {"caller_nid": "actions_transcribeaction_stop", "callee": "clone", "source_file": "C:\\AI_knowledge_workspace\\Handy-main\\src-tauri\\src\\actions.rs", "source_location": "L998"}, {"caller_nid": "actions_transcribeaction_stop", "callee": "now", "source_file": "C:\\AI_knowledge_workspace\\Handy-main\\src-tauri\\src\\actions.rs", "source_location": "L999"}, {"caller_nid": "actions_transcribeaction_stop", "callee": "run_on_main_thread", "source_file": "C:\\AI_knowledge_workspace\\Handy-main\\src-tauri\\src\\actions.rs", "source_location": "L1005"}, {"caller_nid": "actions_transcribeaction_stop", "callee": "paste", "source_file": "C:\\AI_knowledge_workspace\\Handy-main\\src-tauri\\src\\actions.rs", "source_location": "L1006"}, {"caller_nid": "actions_transcribeaction_stop", "callee": "clone", "source_file": "C:\\AI_knowledge_workspace\\Handy-main\\src-tauri\\src\\actions.rs", "source_location": "L1006"}, {"caller_nid": "actions_transcribeaction_stop", "callee": "save_entry", "source_file": "C:\\AI_knowledge_workspace\\Handy-main\\src-tauri\\src\\actions.rs", "source_location": "L1031"}, {"caller_nid": "actions_transcribeaction_stop", "callee": "new", "source_file": "C:\\AI_knowledge_workspace\\Handy-main\\src-tauri\\src\\actions.rs", "source_location": "L1033"}, {"caller_nid": "actions_cancelaction_start", "callee": "cancel_current_operation", "source_file": "C:\\AI_knowledge_workspace\\Handy-main\\src-tauri\\src\\actions.rs", "source_location": "L1063"}]}