{"nodes": [{"id": "c_ai_knowledge_workspace_handy_main_src_components_ui_tooltip_tsx", "label": "Tooltip.tsx", "file_type": "code", "source_file": "C:\\AI_knowledge_workspace\\Handy-main\\src\\components\\ui\\Tooltip.tsx", "source_location": "L1"}, {"id": "tooltip_tooltip", "label": "Tooltip()", "file_type": "code", "source_file": "C:\\AI_knowledge_workspace\\Handy-main\\src\\components\\ui\\Tooltip.tsx", "source_location": "L27"}], "edges": [{"source": "c_ai_knowledge_workspace_handy_main_src_components_ui_tooltip_tsx", "target": "react", "relation": "imports_from", "confidence": "EXTRACTED", "source_file": "C:\\AI_knowledge_workspace\\Handy-main\\src\\components\\ui\\Tooltip.tsx", "source_location": "L1", "weight": 1.0}, {"source": "c_ai_knowledge_workspace_handy_main_src_components_ui_tooltip_tsx", "target": "react_dom", "relation": "imports_from", "confidence": "EXTRACTED", "source_file": "C:\\AI_knowledge_workspace\\Handy-main\\src\\components\\ui\\Tooltip.tsx", "source_location": "L2", "weight": 1.0}, {"source": "c_ai_knowledge_workspace_handy_main_src_components_ui_tooltip_tsx", "target": "workspacemenuchrome", "relation": "imports_from", "confidence": "EXTRACTED", "source_file": "C:\\AI_knowledge_workspace\\Handy-main\\src\\components\\ui\\Tooltip.tsx", "source_location": "L3", "weight": 1.0}, {"source": "c_ai_knowledge_workspace_handy_main_src_components_ui_tooltip_tsx", "target": "workspacefloatinglayer", "relation": "imports_from", "confidence": "EXTRACTED", "source_file": "C:\\AI_knowledge_workspace\\Handy-main\\src\\components\\ui\\Tooltip.tsx", "source_location": "L4", "weight": 1.0}, {"source": "c_ai_knowledge_workspace_handy_main_src_components_ui_tooltip_tsx", "target": "tooltip_tooltip", "relation": "contains", "confidence": "EXTRACTED", "source_file": "C:\\AI_knowledge_workspace\\Handy-main\\src\\components\\ui\\Tooltip.tsx", "source_location": "L27", "weight": 1.0}], "raw_calls": [{"caller_nid": "tooltip_tooltip", "callee": "useState", "source_file": "C:\\AI_knowledge_workspace\\Handy-main\\src\\components\\ui\\Tooltip.tsx", "source_location": "L32"}, {"caller_nid": "tooltip_tooltip", "callee": "useRef", "source_file": "C:\\AI_knowledge_workspace\\Handy-main\\src\\components\\ui\\Tooltip.tsx", "source_location": "L33"}, {"caller_nid": "tooltip_tooltip", "callee": "useCallback", "source_file": "C:\\AI_knowledge_workspace\\Handy-main\\src\\components\\ui\\Tooltip.tsx", "source_location": "L35"}, {"caller_nid": "tooltip_tooltip", "callee": "useEffect", "source_file": "C:\\AI_knowledge_workspace\\Handy-main\\src\\components\\ui\\Tooltip.tsx", "source_location": "L80"}, {"caller_nid": "tooltip_tooltip", "callee": "parseInt", "source_file": "C:\\AI_knowledge_workspace\\Handy-main\\src\\components\\ui\\Tooltip.tsx", "source_location": "L92"}, {"caller_nid": "tooltip_tooltip", "callee": "workspaceTooltipZ", "source_file": "C:\\AI_knowledge_workspace\\Handy-main\\src\\components\\ui\\Tooltip.tsx", "source_location": "L92"}, {"caller_nid": "tooltip_tooltip", "callee": "createPortal", "source_file": "C:\\AI_knowledge_workspace\\Handy-main\\src\\components\\ui\\Tooltip.tsx", "source_location": "L115"}, {"caller_nid": "tooltip_tooltip", "callee": "workspaceMenuSurfaceStyle", "source_file": "C:\\AI_knowledge_workspace\\Handy-main\\src\\components\\ui\\Tooltip.tsx", "source_location": "L119"}]}