{"nodes": [{"id": "c_ai_knowledge_workspace_handy_main_copy_src_ebay_sync_ts", "label": "ebay-sync.ts", "file_type": "code", "source_file": "C:\\AI_knowledge_workspace\\Handy-main\\copy\\src\\ebay-sync.ts", "source_location": "L1"}, {"id": "ebay_sync_inboxindexstatusmessage", "label": "inboxIndexStatusMessage()", "file_type": "code", "source_file": "C:\\AI_knowledge_workspace\\Handy-main\\copy\\src\\ebay-sync.ts", "source_location": "L8"}, {"id": "ebay_sync_threadpagestatusmessage", "label": "threadPageStatusMessage()", "file_type": "code", "source_file": "C:\\AI_knowledge_workspace\\Handy-main\\copy\\src\\ebay-sync.ts", "source_location": "L19"}], "edges": [{"source": "c_ai_knowledge_workspace_handy_main_copy_src_ebay_sync_ts", "target": "c_ai_knowledge_workspace_handy_main_copy_src_types", "relation": "imports_from", "confidence": "EXTRACTED", "source_file": "C:\\AI_knowledge_workspace\\Handy-main\\copy\\src\\ebay-sync.ts", "source_location": "L5", "weight": 1.0}, {"source": "c_ai_knowledge_workspace_handy_main_copy_src_ebay_sync_ts", "target": "ebay_sync_inboxindexstatusmessage", "relation": "contains", "confidence": "EXTRACTED", "source_file": "C:\\AI_knowledge_workspace\\Handy-main\\copy\\src\\ebay-sync.ts", "source_location": "L8", "weight": 1.0}, {"source": "c_ai_knowledge_workspace_handy_main_copy_src_ebay_sync_ts", "target": "ebay_sync_threadpagestatusmessage", "relation": "contains", "confidence": "EXTRACTED", "source_file": "C:\\AI_knowledge_workspace\\Handy-main\\copy\\src\\ebay-sync.ts", "source_location": "L19", "weight": 1.0}], "raw_calls": []}