{"nodes": [{"id": "providerselect", "label": "ProviderSelect.tsx", "file_type": "code", "source_file": "src\\components\\settings\\PostProcessingSettingsApi\\ProviderSelect.tsx", "source_location": "L1"}], "edges": [{"source": "providerselect", "target": "react", "relation": "imports_from", "confidence": "EXTRACTED", "source_file": "src\\components\\settings\\PostProcessingSettingsApi\\ProviderSelect.tsx", "source_location": "L1", "weight": 1.0}, {"source": "providerselect", "target": "dropdown", "relation": "imports_from", "confidence": "EXTRACTED", "source_file": "src\\components\\settings\\PostProcessingSettingsApi\\ProviderSelect.tsx", "source_location": "L2", "weight": 1.0}]}