{"nodes": [{"id": "wav", "label": "wav.rs", "file_type": "code", "source_file": "patches\\vad-rs\\examples\\wav.rs", "source_location": "L1"}, {"id": "wav_main", "label": "main()", "file_type": "code", "source_file": "patches\\vad-rs\\examples\\wav.rs", "source_location": "L10"}], "edges": [{"source": "wav", "target": "wavreader", "relation": "imports_from", "confidence": "EXTRACTED", "source_file": "patches\\vad-rs\\examples\\wav.rs", "source_location": "L7", "weight": 1.0}, {"source": "wav", "target": "vad_rs", "relation": "imports_from", "confidence": "EXTRACTED", "source_file": "patches\\vad-rs\\examples\\wav.rs", "source_location": "L8", "weight": 1.0}, {"source": "wav", "target": "wav_main", "relation": "contains", "confidence": "EXTRACTED", "source_file": "patches\\vad-rs\\examples\\wav.rs", "source_location": "L10", "weight": 1.0}]}