{"nodes": [{"id": "loglevelselector", "label": "LogLevelSelector.tsx", "file_type": "code", "source_file": "Handy-main\\src\\components\\settings\\debug\\LogLevelSelector.tsx", "source_location": "L1"}, {"id": "loglevelselector_loglevelselector", "label": "LogLevelSelector()", "file_type": "code", "source_file": "Handy-main\\src\\components\\settings\\debug\\LogLevelSelector.tsx", "source_location": "L21"}], "edges": [{"source": "loglevelselector", "target": "react", "relation": "imports_from", "confidence": "EXTRACTED", "source_file": "Handy-main\\src\\components\\settings\\debug\\LogLevelSelector.tsx", "source_location": "L1", "weight": 1.0}, {"source": "loglevelselector", "target": "react_i18next", "relation": "imports_from", "confidence": "EXTRACTED", "source_file": "Handy-main\\src\\components\\settings\\debug\\LogLevelSelector.tsx", "source_location": "L2", "weight": 1.0}, {"source": "loglevelselector", "target": "settingcontainer", "relation": "imports_from", "confidence": "EXTRACTED", "source_file": "Handy-main\\src\\components\\settings\\debug\\LogLevelSelector.tsx", "source_location": "L3", "weight": 1.0}, {"source": "loglevelselector", "target": "dropdown", "relation": "imports_from", "confidence": "EXTRACTED", "source_file": "Handy-main\\src\\components\\settings\\debug\\LogLevelSelector.tsx", "source_location": "L4", "weight": 1.0}, {"source": "loglevelselector", "target": "usesettings", "relation": "imports_from", "confidence": "EXTRACTED", "source_file": "Handy-main\\src\\components\\settings\\debug\\LogLevelSelector.tsx", "source_location": "L5", "weight": 1.0}, {"source": "loglevelselector", "target": "bindings", "relation": "imports_from", "confidence": "EXTRACTED", "source_file": "Handy-main\\src\\components\\settings\\debug\\LogLevelSelector.tsx", "source_location": "L6", "weight": 1.0}, {"source": "loglevelselector", "target": "loglevelselector_loglevelselector", "relation": "contains", "confidence": "EXTRACTED", "source_file": "Handy-main\\src\\components\\settings\\debug\\LogLevelSelector.tsx", "source_location": "L21", "weight": 1.0}]}